[{
  "data": {
    "heading": "E",
    "men": 2,
    "contracts": [{
      "amount": 1000,
      "resource": "WOOD"
    }],
    "budget": 30000
  },
  "part": "Engine",
  "time": 1571321256390,
  "meth": "initialize"
},{
  "data": {
    "action": "echo",
    "parameters": {"direction": "N"}
  },
  "part": "Explorer",
  "time": 1571321256394,
  "meth": "takeDecision"
},{
  "data": {
    "cost": 5,
    "extras": {
      "found": "OUT_OF_RANGE",
      "range": 0
    },
    "status": "OK"
  },
  "part": "Engine",
  "time": 1571321256394,
  "meth": "takeDecision"
},{
  "data": {
    "action": "echo",
    "parameters": {"direction": "S"}
  },
  "part": "Explorer",
  "time": 1571321256394,
  "meth": "takeDecision"
},{
  "data": {
    "cost": 7,
    "extras": {
      "found": "OUT_OF_RANGE",
      "range": 52
    },
    "status": "OK"
  },
  "part": "Engine",
  "time": 1571321256395,
  "meth": "takeDecision"
},{
  "data": {
    "action": "heading",
    "parameters": {"direction": "S"}
  },
  "part": "Explorer",
  "time": 1571321256395,
  "meth": "takeDecision"
},{
  "data": {
    "cost": 5,
    "extras": {},
    "status": "OK"
  },
  "part": "Engine",
  "time": 1571321256395,
  "meth": "takeDecision"
},{
  "data": {
    "action": "echo",
    "parameters": {"direction": "E"}
  },
  "part": "Explorer",
  "time": 1571321256395,
  "meth": "takeDecision"
},{
  "data": {
    "cost": 7,
    "extras": {
      "found": "OUT_OF_RANGE",
      "range": 51
    },
    "status": "OK"
  },
  "part": "Engine",
  "time": 1571321256396,
  "meth": "takeDecision"
},{
  "data": {
    "action": "echo",
    "parameters": {"direction": "W"}
  },
  "part": "Explorer",
  "time": 1571321256396,
  "meth": "takeDecision"
},{
  "data": {
    "cost": 4,
    "extras": {
      "found": "OUT_OF_RANGE",
      "range": 1
    },
    "status": "OK"
  },
  "part": "Engine",
  "time": 1571321256396,
  "meth": "takeDecision"
},{
  "data": {"action": "scan"},
  "part": "Explorer",
  "time": 1571321256396,
  "meth": "takeDecision"
},{
  "data": {
    "cost": 5,
    "extras": {
      "creeks": [],
      "biomes": ["OCEAN"],
      "sites": []
    },
    "status": "OK"
  },
  "part": "Engine",
  "time": 1571321256396,
  "meth": "takeDecision"
},{
  "data": {
    "action": "heading",
    "parameters": {"direction": "E"}
  },
  "part": "Explorer",
  "time": 1571321256398,
  "meth": "takeDecision"
},{
  "data": {
    "cost": 5,
    "extras": {},
    "status": "OK"
  },
  "part": "Engine",
  "time": 1571321256398,
  "meth": "takeDecision"
},{
  "data": {
    "action": "echo",
    "parameters": {"direction": "S"}
  },
  "part": "Explorer",
  "time": 1571321256398,
  "meth": "takeDecision"
},{
  "data": {
    "cost": 5,
    "extras": {
      "found": "OUT_OF_RANGE",
      "range": 50
    },
    "status": "OK"
  },
  "part": "Engine",
  "time": 1571321256398,
  "meth": "takeDecision"
},{
  "data": {
    "action": "echo",
    "parameters": {"direction": "N"}
  },
  "part": "Explorer",
  "time": 1571321256399,
  "meth": "takeDecision"
},{
  "data": {
    "cost": 3,
    "extras": {
      "found": "OUT_OF_RANGE",
      "range": 2
    },
    "status": "OK"
  },
  "part": "Engine",
  "time": 1571321256399,
  "meth": "takeDecision"
},{
  "data": {"action": "fly"},
  "part": "Explorer",
  "time": 1571321256399,
  "meth": "takeDecision"
},{
  "data": {
    "cost": 6,
    "extras": {},
    "status": "OK"
  },
  "part": "Engine",
  "time": 1571321256399,
  "meth": "takeDecision"
},{
  "data": {
    "action": "echo",
    "parameters": {"direction": "S"}
  },
  "part": "Explorer",
  "time": 1571321256399,
  "meth": "takeDecision"
},{
  "data": {
    "cost": 8,
    "extras": {
      "found": "OUT_OF_RANGE",
      "range": 50
    },
    "status": "OK"
  },
  "part": "Engine",
  "time": 1571321256399,
  "meth": "takeDecision"
},{
  "data": {
    "action": "echo",
    "parameters": {"direction": "N"}
  },
  "part": "Explorer",
  "time": 1571321256399,
  "meth": "takeDecision"
},{
  "data": {
    "cost": 5,
    "extras": {
      "found": "OUT_OF_RANGE",
      "range": 2
    },
    "status": "OK"
  },
  "part": "Engine",
  "time": 1571321256399,
  "meth": "takeDecision"
},{
  "data": {"action": "fly"},
  "part": "Explorer",
  "time": 1571321256400,
  "meth": "takeDecision"
},{
  "data": {
    "cost": 4,
    "extras": {},
    "status": "OK"
  },
  "part": "Engine",
  "time": 1571321256400,
  "meth": "takeDecision"
},{
  "data": {
    "action": "echo",
    "parameters": {"direction": "S"}
  },
  "part": "Explorer",
  "time": 1571321256400,
  "meth": "takeDecision"
},{
  "data": {
    "cost": 5,
    "extras": {
      "found": "OUT_OF_RANGE",
      "range": 50
    },
    "status": "OK"
  },
  "part": "Engine",
  "time": 1571321256400,
  "meth": "takeDecision"
},{
  "data": {
    "action": "echo",
    "parameters": {"direction": "N"}
  },
  "part": "Explorer",
  "time": 1571321256400,
  "meth": "takeDecision"
},{
  "data": {
    "cost": 4,
    "extras": {
      "found": "OUT_OF_RANGE",
      "range": 2
    },
    "status": "OK"
  },
  "part": "Engine",
  "time": 1571321256400,
  "meth": "takeDecision"
},{
  "data": {"action": "fly"},
  "part": "Explorer",
  "time": 1571321256400,
  "meth": "takeDecision"
},{
  "data": {
    "cost": 5,
    "extras": {},
    "status": "OK"
  },
  "part": "Engine",
  "time": 1571321256400,
  "meth": "takeDecision"
},{
  "data": {
    "action": "echo",
    "parameters": {"direction": "S"}
  },
  "part": "Explorer",
  "time": 1571321256401,
  "meth": "takeDecision"
},{
  "data": {
    "cost": 6,
    "extras": {
      "found": "OUT_OF_RANGE",
      "range": 50
    },
    "status": "OK"
  },
  "part": "Engine",
  "time": 1571321256401,
  "meth": "takeDecision"
},{
  "data": {
    "action": "echo",
    "parameters": {"direction": "N"}
  },
  "part": "Explorer",
  "time": 1571321256401,
  "meth": "takeDecision"
},{
  "data": {
    "cost": 5,
    "extras": {
      "found": "OUT_OF_RANGE",
      "range": 2
    },
    "status": "OK"
  },
  "part": "Engine",
  "time": 1571321256401,
  "meth": "takeDecision"
},{
  "data": {"action": "fly"},
  "part": "Explorer",
  "time": 1571321256401,
  "meth": "takeDecision"
},{
  "data": {
    "cost": 3,
    "extras": {},
    "status": "OK"
  },
  "part": "Engine",
  "time": 1571321256401,
  "meth": "takeDecision"
},{
  "data": {
    "action": "echo",
    "parameters": {"direction": "S"}
  },
  "part": "Explorer",
  "time": 1571321256401,
  "meth": "takeDecision"
},{
  "data": {
    "cost": 4,
    "extras": {
      "found": "OUT_OF_RANGE",
      "range": 50
    },
    "status": "OK"
  },
  "part": "Engine",
  "time": 1571321256402,
  "meth": "takeDecision"
},{
  "data": {
    "action": "echo",
    "parameters": {"direction": "N"}
  },
  "part": "Explorer",
  "time": 1571321256402,
  "meth": "takeDecision"
},{
  "data": {
    "cost": 4,
    "extras": {
      "found": "OUT_OF_RANGE",
      "range": 2
    },
    "status": "OK"
  },
  "part": "Engine",
  "time": 1571321256402,
  "meth": "takeDecision"
},{
  "data": {"action": "fly"},
  "part": "Explorer",
  "time": 1571321256402,
  "meth": "takeDecision"
},{
  "data": {
    "cost": 4,
    "extras": {},
    "status": "OK"
  },
  "part": "Engine",
  "time": 1571321256402,
  "meth": "takeDecision"
},{
  "data": {
    "action": "echo",
    "parameters": {"direction": "S"}
  },
  "part": "Explorer",
  "time": 1571321256402,
  "meth": "takeDecision"
},{
  "data": {
    "cost": 7,
    "extras": {
      "found": "OUT_OF_RANGE",
      "range": 50
    },
    "status": "OK"
  },
  "part": "Engine",
  "time": 1571321256402,
  "meth": "takeDecision"
},{
  "data": {
    "action": "echo",
    "parameters": {"direction": "N"}
  },
  "part": "Explorer",
  "time": 1571321256402,
  "meth": "takeDecision"
},{
  "data": {
    "cost": 4,
    "extras": {
      "found": "OUT_OF_RANGE",
      "range": 2
    },
    "status": "OK"
  },
  "part": "Engine",
  "time": 1571321256403,
  "meth": "takeDecision"
},{
  "data": {"action": "fly"},
  "part": "Explorer",
  "time": 1571321256403,
  "meth": "takeDecision"
},{
  "data": {
    "cost": 4,
    "extras": {},
    "status": "OK"
  },
  "part": "Engine",
  "time": 1571321256403,
  "meth": "takeDecision"
},{
  "data": {
    "action": "echo",
    "parameters": {"direction": "S"}
  },
  "part": "Explorer",
  "time": 1571321256403,
  "meth": "takeDecision"
},{
  "data": {
    "cost": 6,
    "extras": {
      "found": "OUT_OF_RANGE",
      "range": 50
    },
    "status": "OK"
  },
  "part": "Engine",
  "time": 1571321256403,
  "meth": "takeDecision"
},{
  "data": {
    "action": "echo",
    "parameters": {"direction": "N"}
  },
  "part": "Explorer",
  "time": 1571321256403,
  "meth": "takeDecision"
},{
  "data": {
    "cost": 4,
    "extras": {
      "found": "OUT_OF_RANGE",
      "range": 2
    },
    "status": "OK"
  },
  "part": "Engine",
  "time": 1571321256403,
  "meth": "takeDecision"
},{
  "data": {"action": "fly"},
  "part": "Explorer",
  "time": 1571321256403,
  "meth": "takeDecision"
},{
  "data": {
    "cost": 4,
    "extras": {},
    "status": "OK"
  },
  "part": "Engine",
  "time": 1571321256403,
  "meth": "takeDecision"
},{
  "data": {
    "action": "echo",
    "parameters": {"direction": "S"}
  },
  "part": "Explorer",
  "time": 1571321256403,
  "meth": "takeDecision"
},{
  "data": {
    "cost": 3,
    "extras": {
      "found": "OUT_OF_RANGE",
      "range": 50
    },
    "status": "OK"
  },
  "part": "Engine",
  "time": 1571321256404,
  "meth": "takeDecision"
},{
  "data": {
    "action": "echo",
    "parameters": {"direction": "N"}
  },
  "part": "Explorer",
  "time": 1571321256404,
  "meth": "takeDecision"
},{
  "data": {
    "cost": 4,
    "extras": {
      "found": "OUT_OF_RANGE",
      "range": 2
    },
    "status": "OK"
  },
  "part": "Engine",
  "time": 1571321256404,
  "meth": "takeDecision"
},{
  "data": {"action": "fly"},
  "part": "Explorer",
  "time": 1571321256404,
  "meth": "takeDecision"
},{
  "data": {
    "cost": 5,
    "extras": {},
    "status": "OK"
  },
  "part": "Engine",
  "time": 1571321256404,
  "meth": "takeDecision"
},{
  "data": {
    "action": "echo",
    "parameters": {"direction": "S"}
  },
  "part": "Explorer",
  "time": 1571321256404,
  "meth": "takeDecision"
},{
  "data": {
    "cost": 4,
    "extras": {
      "found": "GROUND",
      "range": 26
    },
    "status": "OK"
  },
  "part": "Engine",
  "time": 1571321256404,
  "meth": "takeDecision"
},{
  "data": {"action": "fly"},
  "part": "Explorer",
  "time": 1571321256404,
  "meth": "takeDecision"
},{
  "data": {
    "cost": 2,
    "extras": {},
    "status": "OK"
  },
  "part": "Engine",
  "time": 1571321256405,
  "meth": "takeDecision"
},{
  "data": {
    "action": "echo",
    "parameters": {"direction": "S"}
  },
  "part": "Explorer",
  "time": 1571321256405,
  "meth": "takeDecision"
},{
  "data": {
    "cost": 4,
    "extras": {
      "found": "GROUND",
      "range": 19
    },
    "status": "OK"
  },
  "part": "Engine",
  "time": 1571321256405,
  "meth": "takeDecision"
},{
  "data": {"action": "fly"},
  "part": "Explorer",
  "time": 1571321256405,
  "meth": "takeDecision"
},{
  "data": {
    "cost": 3,
    "extras": {},
    "status": "OK"
  },
  "part": "Engine",
  "time": 1571321256405,
  "meth": "takeDecision"
},{
  "data": {
    "action": "echo",
    "parameters": {"direction": "S"}
  },
  "part": "Explorer",
  "time": 1571321256405,
  "meth": "takeDecision"
},{
  "data": {
    "cost": 4,
    "extras": {
      "found": "GROUND",
      "range": 18
    },
    "status": "OK"
  },
  "part": "Engine",
  "time": 1571321256405,
  "meth": "takeDecision"
},{
  "data": {"action": "fly"},
  "part": "Explorer",
  "time": 1571321256405,
  "meth": "takeDecision"
},{
  "data": {
    "cost": 6,
    "extras": {},
    "status": "OK"
  },
  "part": "Engine",
  "time": 1571321256405,
  "meth": "takeDecision"
},{
  "data": {
    "action": "echo",
    "parameters": {"direction": "S"}
  },
  "part": "Explorer",
  "time": 1571321256405,
  "meth": "takeDecision"
},{
  "data": {
    "cost": 3,
    "extras": {
      "found": "GROUND",
      "range": 16
    },
    "status": "OK"
  },
  "part": "Engine",
  "time": 1571321256405,
  "meth": "takeDecision"
},{
  "data": {"action": "fly"},
  "part": "Explorer",
  "time": 1571321256405,
  "meth": "takeDecision"
},{
  "data": {
    "cost": 3,
    "extras": {},
    "status": "OK"
  },
  "part": "Engine",
  "time": 1571321256405,
  "meth": "takeDecision"
},{
  "data": {
    "action": "echo",
    "parameters": {"direction": "S"}
  },
  "part": "Explorer",
  "time": 1571321256405,
  "meth": "takeDecision"
},{
  "data": {
    "cost": 4,
    "extras": {
      "found": "GROUND",
      "range": 14
    },
    "status": "OK"
  },
  "part": "Engine",
  "time": 1571321256405,
  "meth": "takeDecision"
},{
  "data": {"action": "fly"},
  "part": "Explorer",
  "time": 1571321256405,
  "meth": "takeDecision"
},{
  "data": {
    "cost": 5,
    "extras": {},
    "status": "OK"
  },
  "part": "Engine",
  "time": 1571321256406,
  "meth": "takeDecision"
},{
  "data": {
    "action": "echo",
    "parameters": {"direction": "S"}
  },
  "part": "Explorer",
  "time": 1571321256406,
  "meth": "takeDecision"
},{
  "data": {
    "cost": 7,
    "extras": {
      "found": "GROUND",
      "range": 13
    },
    "status": "OK"
  },
  "part": "Engine",
  "time": 1571321256406,
  "meth": "takeDecision"
},{
  "data": {"action": "fly"},
  "part": "Explorer",
  "time": 1571321256406,
  "meth": "takeDecision"
},{
  "data": {
    "cost": 2,
    "extras": {},
    "status": "OK"
  },
  "part": "Engine",
  "time": 1571321256406,
  "meth": "takeDecision"
},{
  "data": {
    "action": "echo",
    "parameters": {"direction": "S"}
  },
  "part": "Explorer",
  "time": 1571321256406,
  "meth": "takeDecision"
},{
  "data": {
    "cost": 6,
    "extras": {
      "found": "GROUND",
      "range": 11
    },
    "status": "OK"
  },
  "part": "Engine",
  "time": 1571321256406,
  "meth": "takeDecision"
},{
  "data": {"action": "fly"},
  "part": "Explorer",
  "time": 1571321256406,
  "meth": "takeDecision"
},{
  "data": {
    "cost": 3,
    "extras": {},
    "status": "OK"
  },
  "part": "Engine",
  "time": 1571321256406,
  "meth": "takeDecision"
},{
  "data": {
    "action": "echo",
    "parameters": {"direction": "S"}
  },
  "part": "Explorer",
  "time": 1571321256406,
  "meth": "takeDecision"
},{
  "data": {
    "cost": 5,
    "extras": {
      "found": "GROUND",
      "range": 11
    },
    "status": "OK"
  },
  "part": "Engine",
  "time": 1571321256406,
  "meth": "takeDecision"
},{
  "data": {"action": "fly"},
  "part": "Explorer",
  "time": 1571321256406,
  "meth": "takeDecision"
},{
  "data": {
    "cost": 3,
    "extras": {},
    "status": "OK"
  },
  "part": "Engine",
  "time": 1571321256406,
  "meth": "takeDecision"
},{
  "data": {
    "action": "echo",
    "parameters": {"direction": "S"}
  },
  "part": "Explorer",
  "time": 1571321256406,
  "meth": "takeDecision"
},{
  "data": {
    "cost": 5,
    "extras": {
      "found": "GROUND",
      "range": 10
    },
    "status": "OK"
  },
  "part": "Engine",
  "time": 1571321256406,
  "meth": "takeDecision"
},{
  "data": {"action": "fly"},
  "part": "Explorer",
  "time": 1571321256406,
  "meth": "takeDecision"
},{
  "data": {
    "cost": 4,
    "extras": {},
    "status": "OK"
  },
  "part": "Engine",
  "time": 1571321256406,
  "meth": "takeDecision"
},{
  "data": {
    "action": "echo",
    "parameters": {"direction": "S"}
  },
  "part": "Explorer",
  "time": 1571321256406,
  "meth": "takeDecision"
},{
  "data": {
    "cost": 4,
    "extras": {
      "found": "GROUND",
      "range": 10
    },
    "status": "OK"
  },
  "part": "Engine",
  "time": 1571321256406,
  "meth": "takeDecision"
},{
  "data": {"action": "fly"},
  "part": "Explorer",
  "time": 1571321256406,
  "meth": "takeDecision"
},{
  "data": {
    "cost": 5,
    "extras": {},
    "status": "OK"
  },
  "part": "Engine",
  "time": 1571321256406,
  "meth": "takeDecision"
},{
  "data": {
    "action": "echo",
    "parameters": {"direction": "S"}
  },
  "part": "Explorer",
  "time": 1571321256407,
  "meth": "takeDecision"
},{
  "data": {
    "cost": 6,
    "extras": {
      "found": "GROUND",
      "range": 9
    },
    "status": "OK"
  },
  "part": "Engine",
  "time": 1571321256407,
  "meth": "takeDecision"
},{
  "data": {"action": "fly"},
  "part": "Explorer",
  "time": 1571321256407,
  "meth": "takeDecision"
},{
  "data": {
    "cost": 5,
    "extras": {},
    "status": "OK"
  },
  "part": "Engine",
  "time": 1571321256407,
  "meth": "takeDecision"
},{
  "data": {
    "action": "echo",
    "parameters": {"direction": "S"}
  },
  "part": "Explorer",
  "time": 1571321256407,
  "meth": "takeDecision"
},{
  "data": {
    "cost": 6,
    "extras": {
      "found": "GROUND",
      "range": 8
    },
    "status": "OK"
  },
  "part": "Engine",
  "time": 1571321256407,
  "meth": "takeDecision"
},{
  "data": {"action": "fly"},
  "part": "Explorer",
  "time": 1571321256407,
  "meth": "takeDecision"
},{
  "data": {
    "cost": 3,
    "extras": {},
    "status": "OK"
  },
  "part": "Engine",
  "time": 1571321256407,
  "meth": "takeDecision"
},{
  "data": {
    "action": "echo",
    "parameters": {"direction": "S"}
  },
  "part": "Explorer",
  "time": 1571321256407,
  "meth": "takeDecision"
},{
  "data": {
    "cost": 5,
    "extras": {
      "found": "GROUND",
      "range": 9
    },
    "status": "OK"
  },
  "part": "Engine",
  "time": 1571321256407,
  "meth": "takeDecision"
},{
  "data": {"action": "fly"},
  "part": "Explorer",
  "time": 1571321256407,
  "meth": "takeDecision"
},{
  "data": {
    "cost": 3,
    "extras": {},
    "status": "OK"
  },
  "part": "Engine",
  "time": 1571321256407,
  "meth": "takeDecision"
},{
  "data": {
    "action": "echo",
    "parameters": {"direction": "S"}
  },
  "part": "Explorer",
  "time": 1571321256407,
  "meth": "takeDecision"
},{
  "data": {
    "cost": 7,
    "extras": {
      "found": "GROUND",
      "range": 9
    },
    "status": "OK"
  },
  "part": "Engine",
  "time": 1571321256407,
  "meth": "takeDecision"
},{
  "data": {"action": "fly"},
  "part": "Explorer",
  "time": 1571321256407,
  "meth": "takeDecision"
},{
  "data": {
    "cost": 6,
    "extras": {},
    "status": "OK"
  },
  "part": "Engine",
  "time": 1571321256407,
  "meth": "takeDecision"
},{
  "data": {
    "action": "echo",
    "parameters": {"direction": "S"}
  },
  "part": "Explorer",
  "time": 1571321256407,
  "meth": "takeDecision"
},{
  "data": {
    "cost": 5,
    "extras": {
      "found": "GROUND",
      "range": 8
    },
    "status": "OK"
  },
  "part": "Engine",
  "time": 1571321256407,
  "meth": "takeDecision"
},{
  "data": {"action": "fly"},
  "part": "Explorer",
  "time": 1571321256408,
  "meth": "takeDecision"
},{
  "data": {
    "cost": 3,
    "extras": {},
    "status": "OK"
  },
  "part": "Engine",
  "time": 1571321256408,
  "meth": "takeDecision"
},{
  "data": {
    "action": "echo",
    "parameters": {"direction": "S"}
  },
  "part": "Explorer",
  "time": 1571321256408,
  "meth": "takeDecision"
},{
  "data": {
    "cost": 5,
    "extras": {
      "found": "GROUND",
      "range": 8
    },
    "status": "OK"
  },
  "part": "Engine",
  "time": 1571321256408,
  "meth": "takeDecision"
},{
  "data": {"action": "fly"},
  "part": "Explorer",
  "time": 1571321256408,
  "meth": "takeDecision"
},{
  "data": {
    "cost": 5,
    "extras": {},
    "status": "OK"
  },
  "part": "Engine",
  "time": 1571321256408,
  "meth": "takeDecision"
},{
  "data": {
    "action": "echo",
    "parameters": {"direction": "S"}
  },
  "part": "Explorer",
  "time": 1571321256408,
  "meth": "takeDecision"
},{
  "data": {
    "cost": 7,
    "extras": {
      "found": "GROUND",
      "range": 8
    },
    "status": "OK"
  },
  "part": "Engine",
  "time": 1571321256408,
  "meth": "takeDecision"
},{
  "data": {"action": "fly"},
  "part": "Explorer",
  "time": 1571321256408,
  "meth": "takeDecision"
},{
  "data": {
    "cost": 3,
    "extras": {},
    "status": "OK"
  },
  "part": "Engine",
  "time": 1571321256408,
  "meth": "takeDecision"
},{
  "data": {
    "action": "echo",
    "parameters": {"direction": "S"}
  },
  "part": "Explorer",
  "time": 1571321256408,
  "meth": "takeDecision"
},{
  "data": {
    "cost": 6,
    "extras": {
      "found": "GROUND",
      "range": 7
    },
    "status": "OK"
  },
  "part": "Engine",
  "time": 1571321256408,
  "meth": "takeDecision"
},{
  "data": {"action": "fly"},
  "part": "Explorer",
  "time": 1571321256408,
  "meth": "takeDecision"
},{
  "data": {
    "cost": 2,
    "extras": {},
    "status": "OK"
  },
  "part": "Engine",
  "time": 1571321256408,
  "meth": "takeDecision"
},{
  "data": {
    "action": "echo",
    "parameters": {"direction": "S"}
  },
  "part": "Explorer",
  "time": 1571321256408,
  "meth": "takeDecision"
},{
  "data": {
    "cost": 4,
    "extras": {
      "found": "GROUND",
      "range": 8
    },
    "status": "OK"
  },
  "part": "Engine",
  "time": 1571321256408,
  "meth": "takeDecision"
},{
  "data": {"action": "fly"},
  "part": "Explorer",
  "time": 1571321256408,
  "meth": "takeDecision"
},{
  "data": {
    "cost": 6,
    "extras": {},
    "status": "OK"
  },
  "part": "Engine",
  "time": 1571321256408,
  "meth": "takeDecision"
},{
  "data": {
    "action": "echo",
    "parameters": {"direction": "S"}
  },
  "part": "Explorer",
  "time": 1571321256409,
  "meth": "takeDecision"
},{
  "data": {
    "cost": 5,
    "extras": {
      "found": "GROUND",
      "range": 8
    },
    "status": "OK"
  },
  "part": "Engine",
  "time": 1571321256409,
  "meth": "takeDecision"
},{
  "data": {"action": "fly"},
  "part": "Explorer",
  "time": 1571321256409,
  "meth": "takeDecision"
},{
  "data": {
    "cost": 3,
    "extras": {},
    "status": "OK"
  },
  "part": "Engine",
  "time": 1571321256409,
  "meth": "takeDecision"
},{
  "data": {
    "action": "echo",
    "parameters": {"direction": "S"}
  },
  "part": "Explorer",
  "time": 1571321256409,
  "meth": "takeDecision"
},{
  "data": {
    "cost": 3,
    "extras": {
      "found": "GROUND",
      "range": 8
    },
    "status": "OK"
  },
  "part": "Engine",
  "time": 1571321256409,
  "meth": "takeDecision"
},{
  "data": {"action": "fly"},
  "part": "Explorer",
  "time": 1571321256409,
  "meth": "takeDecision"
},{
  "data": {
    "cost": 3,
    "extras": {},
    "status": "OK"
  },
  "part": "Engine",
  "time": 1571321256409,
  "meth": "takeDecision"
},{
  "data": {
    "action": "echo",
    "parameters": {"direction": "S"}
  },
  "part": "Explorer",
  "time": 1571321256409,
  "meth": "takeDecision"
},{
  "data": {
    "cost": 4,
    "extras": {
      "found": "GROUND",
      "range": 9
    },
    "status": "OK"
  },
  "part": "Engine",
  "time": 1571321256409,
  "meth": "takeDecision"
},{
  "data": {"action": "fly"},
  "part": "Explorer",
  "time": 1571321256409,
  "meth": "takeDecision"
},{
  "data": {
    "cost": 3,
    "extras": {},
    "status": "OK"
  },
  "part": "Engine",
  "time": 1571321256409,
  "meth": "takeDecision"
},{
  "data": {
    "action": "echo",
    "parameters": {"direction": "S"}
  },
  "part": "Explorer",
  "time": 1571321256409,
  "meth": "takeDecision"
},{
  "data": {
    "cost": 7,
    "extras": {
      "found": "GROUND",
      "range": 9
    },
    "status": "OK"
  },
  "part": "Engine",
  "time": 1571321256409,
  "meth": "takeDecision"
},{
  "data": {"action": "fly"},
  "part": "Explorer",
  "time": 1571321256409,
  "meth": "takeDecision"
},{
  "data": {
    "cost": 3,
    "extras": {},
    "status": "OK"
  },
  "part": "Engine",
  "time": 1571321256409,
  "meth": "takeDecision"
},{
  "data": {
    "action": "echo",
    "parameters": {"direction": "S"}
  },
  "part": "Explorer",
  "time": 1571321256409,
  "meth": "takeDecision"
},{
  "data": {
    "cost": 4,
    "extras": {
      "found": "GROUND",
      "range": 9
    },
    "status": "OK"
  },
  "part": "Engine",
  "time": 1571321256409,
  "meth": "takeDecision"
},{
  "data": {"action": "fly"},
  "part": "Explorer",
  "time": 1571321256409,
  "meth": "takeDecision"
},{
  "data": {
    "cost": 4,
    "extras": {},
    "status": "OK"
  },
  "part": "Engine",
  "time": 1571321256410,
  "meth": "takeDecision"
},{
  "data": {
    "action": "echo",
    "parameters": {"direction": "S"}
  },
  "part": "Explorer",
  "time": 1571321256410,
  "meth": "takeDecision"
},{
  "data": {
    "cost": 4,
    "extras": {
      "found": "GROUND",
      "range": 10
    },
    "status": "OK"
  },
  "part": "Engine",
  "time": 1571321256410,
  "meth": "takeDecision"
},{
  "data": {"action": "fly"},
  "part": "Explorer",
  "time": 1571321256410,
  "meth": "takeDecision"
},{
  "data": {
    "cost": 4,
    "extras": {},
    "status": "OK"
  },
  "part": "Engine",
  "time": 1571321256410,
  "meth": "takeDecision"
},{
  "data": {
    "action": "echo",
    "parameters": {"direction": "S"}
  },
  "part": "Explorer",
  "time": 1571321256410,
  "meth": "takeDecision"
},{
  "data": {
    "cost": 5,
    "extras": {
      "found": "GROUND",
      "range": 11
    },
    "status": "OK"
  },
  "part": "Engine",
  "time": 1571321256410,
  "meth": "takeDecision"
},{
  "data": {"action": "fly"},
  "part": "Explorer",
  "time": 1571321256410,
  "meth": "takeDecision"
},{
  "data": {
    "cost": 5,
    "extras": {},
    "status": "OK"
  },
  "part": "Engine",
  "time": 1571321256410,
  "meth": "takeDecision"
},{
  "data": {
    "action": "echo",
    "parameters": {"direction": "S"}
  },
  "part": "Explorer",
  "time": 1571321256410,
  "meth": "takeDecision"
},{
  "data": {
    "cost": 5,
    "extras": {
      "found": "GROUND",
      "range": 12
    },
    "status": "OK"
  },
  "part": "Engine",
  "time": 1571321256410,
  "meth": "takeDecision"
},{
  "data": {"action": "fly"},
  "part": "Explorer",
  "time": 1571321256410,
  "meth": "takeDecision"
},{
  "data": {
    "cost": 5,
    "extras": {},
    "status": "OK"
  },
  "part": "Engine",
  "time": 1571321256410,
  "meth": "takeDecision"
},{
  "data": {
    "action": "echo",
    "parameters": {"direction": "S"}
  },
  "part": "Explorer",
  "time": 1571321256410,
  "meth": "takeDecision"
},{
  "data": {
    "cost": 5,
    "extras": {
      "found": "GROUND",
      "range": 12
    },
    "status": "OK"
  },
  "part": "Engine",
  "time": 1571321256410,
  "meth": "takeDecision"
},{
  "data": {"action": "fly"},
  "part": "Explorer",
  "time": 1571321256410,
  "meth": "takeDecision"
},{
  "data": {
    "cost": 3,
    "extras": {},
    "status": "OK"
  },
  "part": "Engine",
  "time": 1571321256410,
  "meth": "takeDecision"
},{
  "data": {
    "action": "echo",
    "parameters": {"direction": "S"}
  },
  "part": "Explorer",
  "time": 1571321256410,
  "meth": "takeDecision"
},{
  "data": {
    "cost": 4,
    "extras": {
      "found": "GROUND",
      "range": 13
    },
    "status": "OK"
  },
  "part": "Engine",
  "time": 1571321256410,
  "meth": "takeDecision"
},{
  "data": {"action": "fly"},
  "part": "Explorer",
  "time": 1571321256411,
  "meth": "takeDecision"
},{
  "data": {
    "cost": 3,
    "extras": {},
    "status": "OK"
  },
  "part": "Engine",
  "time": 1571321256411,
  "meth": "takeDecision"
},{
  "data": {
    "action": "echo",
    "parameters": {"direction": "S"}
  },
  "part": "Explorer",
  "time": 1571321256411,
  "meth": "takeDecision"
},{
  "data": {
    "cost": 5,
    "extras": {
      "found": "GROUND",
      "range": 15
    },
    "status": "OK"
  },
  "part": "Engine",
  "time": 1571321256411,
  "meth": "takeDecision"
},{
  "data": {"action": "fly"},
  "part": "Explorer",
  "time": 1571321256411,
  "meth": "takeDecision"
},{
  "data": {
    "cost": 6,
    "extras": {},
    "status": "OK"
  },
  "part": "Engine",
  "time": 1571321256411,
  "meth": "takeDecision"
},{
  "data": {
    "action": "echo",
    "parameters": {"direction": "S"}
  },
  "part": "Explorer",
  "time": 1571321256411,
  "meth": "takeDecision"
},{
  "data": {
    "cost": 6,
    "extras": {
      "found": "GROUND",
      "range": 16
    },
    "status": "OK"
  },
  "part": "Engine",
  "time": 1571321256411,
  "meth": "takeDecision"
},{
  "data": {"action": "fly"},
  "part": "Explorer",
  "time": 1571321256411,
  "meth": "takeDecision"
},{
  "data": {
    "cost": 3,
    "extras": {},
    "status": "OK"
  },
  "part": "Engine",
  "time": 1571321256411,
  "meth": "takeDecision"
},{
  "data": {
    "action": "echo",
    "parameters": {"direction": "S"}
  },
  "part": "Explorer",
  "time": 1571321256411,
  "meth": "takeDecision"
},{
  "data": {
    "cost": 5,
    "extras": {
      "found": "GROUND",
      "range": 19
    },
    "status": "OK"
  },
  "part": "Engine",
  "time": 1571321256411,
  "meth": "takeDecision"
},{
  "data": {"action": "fly"},
  "part": "Explorer",
  "time": 1571321256411,
  "meth": "takeDecision"
},{
  "data": {
    "cost": 5,
    "extras": {},
    "status": "OK"
  },
  "part": "Engine",
  "time": 1571321256411,
  "meth": "takeDecision"
},{
  "data": {
    "action": "echo",
    "parameters": {"direction": "S"}
  },
  "part": "Explorer",
  "time": 1571321256411,
  "meth": "takeDecision"
},{
  "data": {
    "cost": 7,
    "extras": {
      "found": "GROUND",
      "range": 24
    },
    "status": "OK"
  },
  "part": "Engine",
  "time": 1571321256412,
  "meth": "takeDecision"
},{
  "data": {"action": "fly"},
  "part": "Explorer",
  "time": 1571321256412,
  "meth": "takeDecision"
},{
  "data": {
    "cost": 5,
    "extras": {},
    "status": "OK"
  },
  "part": "Engine",
  "time": 1571321256412,
  "meth": "takeDecision"
},{
  "data": {
    "action": "echo",
    "parameters": {"direction": "S"}
  },
  "part": "Explorer",
  "time": 1571321256412,
  "meth": "takeDecision"
},{
  "data": {
    "cost": 5,
    "extras": {
      "found": "OUT_OF_RANGE",
      "range": 50
    },
    "status": "OK"
  },
  "part": "Engine",
  "time": 1571321256412,
  "meth": "takeDecision"
},{
  "data": {
    "action": "echo",
    "parameters": {"direction": "N"}
  },
  "part": "Explorer",
  "time": 1571321256412,
  "meth": "takeDecision"
},{
  "data": {
    "cost": 3,
    "extras": {
      "found": "OUT_OF_RANGE",
      "range": 2
    },
    "status": "OK"
  },
  "part": "Engine",
  "time": 1571321256412,
  "meth": "takeDecision"
},{
  "data": {
    "action": "heading",
    "parameters": {"direction": "S"}
  },
  "part": "Explorer",
  "time": 1571321256412,
  "meth": "takeDecision"
},{
  "data": {
    "cost": 6,
    "extras": {},
    "status": "OK"
  },
  "part": "Engine",
  "time": 1571321256412,
  "meth": "takeDecision"
},{
  "data": {
    "action": "echo",
    "parameters": {"direction": "E"}
  },
  "part": "Explorer",
  "time": 1571321256412,
  "meth": "takeDecision"
},{
  "data": {
    "cost": 5,
    "extras": {
      "found": "OUT_OF_RANGE",
      "range": 8
    },
    "status": "OK"
  },
  "part": "Engine",
  "time": 1571321256413,
  "meth": "takeDecision"
},{
  "data": {
    "action": "echo",
    "parameters": {"direction": "W"}
  },
  "part": "Explorer",
  "time": 1571321256413,
  "meth": "takeDecision"
},{
  "data": {
    "cost": 4,
    "extras": {
      "found": "OUT_OF_RANGE",
      "range": 44
    },
    "status": "OK"
  },
  "part": "Engine",
  "time": 1571321256413,
  "meth": "takeDecision"
},{
  "data": {"action": "fly"},
  "part": "Explorer",
  "time": 1571321256413,
  "meth": "takeDecision"
},{
  "data": {
    "cost": 3,
    "extras": {},
    "status": "OK"
  },
  "part": "Engine",
  "time": 1571321256413,
  "meth": "takeDecision"
},{
  "data": {
    "action": "echo",
    "parameters": {"direction": "E"}
  },
  "part": "Explorer",
  "time": 1571321256413,
  "meth": "takeDecision"
},{
  "data": {
    "cost": 4,
    "extras": {
      "found": "OUT_OF_RANGE",
      "range": 8
    },
    "status": "OK"
  },
  "part": "Engine",
  "time": 1571321256413,
  "meth": "takeDecision"
},{
  "data": {
    "action": "echo",
    "parameters": {"direction": "W"}
  },
  "part": "Explorer",
  "time": 1571321256413,
  "meth": "takeDecision"
},{
  "data": {
    "cost": 5,
    "extras": {
      "found": "OUT_OF_RANGE",
      "range": 44
    },
    "status": "OK"
  },
  "part": "Engine",
  "time": 1571321256413,
  "meth": "takeDecision"
},{
  "data": {"action": "fly"},
  "part": "Explorer",
  "time": 1571321256413,
  "meth": "takeDecision"
},{
  "data": {
    "cost": 3,
    "extras": {},
    "status": "OK"
  },
  "part": "Engine",
  "time": 1571321256413,
  "meth": "takeDecision"
},{
  "data": {
    "action": "echo",
    "parameters": {"direction": "E"}
  },
  "part": "Explorer",
  "time": 1571321256413,
  "meth": "takeDecision"
},{
  "data": {
    "cost": 5,
    "extras": {
      "found": "OUT_OF_RANGE",
      "range": 8
    },
    "status": "OK"
  },
  "part": "Engine",
  "time": 1571321256413,
  "meth": "takeDecision"
},{
  "data": {
    "action": "echo",
    "parameters": {"direction": "W"}
  },
  "part": "Explorer",
  "time": 1571321256414,
  "meth": "takeDecision"
},{
  "data": {
    "cost": 4,
    "extras": {
      "found": "OUT_OF_RANGE",
      "range": 44
    },
    "status": "OK"
  },
  "part": "Engine",
  "time": 1571321256414,
  "meth": "takeDecision"
},{
  "data": {"action": "fly"},
  "part": "Explorer",
  "time": 1571321256414,
  "meth": "takeDecision"
},{
  "data": {
    "cost": 4,
    "extras": {},
    "status": "OK"
  },
  "part": "Engine",
  "time": 1571321256414,
  "meth": "takeDecision"
},{
  "data": {
    "action": "echo",
    "parameters": {"direction": "E"}
  },
  "part": "Explorer",
  "time": 1571321256414,
  "meth": "takeDecision"
},{
  "data": {
    "cost": 6,
    "extras": {
      "found": "OUT_OF_RANGE",
      "range": 8
    },
    "status": "OK"
  },
  "part": "Engine",
  "time": 1571321256414,
  "meth": "takeDecision"
},{
  "data": {
    "action": "echo",
    "parameters": {"direction": "W"}
  },
  "part": "Explorer",
  "time": 1571321256414,
  "meth": "takeDecision"
},{
  "data": {
    "cost": 7,
    "extras": {
      "found": "OUT_OF_RANGE",
      "range": 44
    },
    "status": "OK"
  },
  "part": "Engine",
  "time": 1571321256414,
  "meth": "takeDecision"
},{
  "data": {"action": "fly"},
  "part": "Explorer",
  "time": 1571321256414,
  "meth": "takeDecision"
},{
  "data": {
    "cost": 3,
    "extras": {},
    "status": "OK"
  },
  "part": "Engine",
  "time": 1571321256414,
  "meth": "takeDecision"
},{
  "data": {
    "action": "echo",
    "parameters": {"direction": "E"}
  },
  "part": "Explorer",
  "time": 1571321256415,
  "meth": "takeDecision"
},{
  "data": {
    "cost": 6,
    "extras": {
      "found": "OUT_OF_RANGE",
      "range": 8
    },
    "status": "OK"
  },
  "part": "Engine",
  "time": 1571321256415,
  "meth": "takeDecision"
},{
  "data": {
    "action": "echo",
    "parameters": {"direction": "W"}
  },
  "part": "Explorer",
  "time": 1571321256415,
  "meth": "takeDecision"
},{
  "data": {
    "cost": 3,
    "extras": {
      "found": "OUT_OF_RANGE",
      "range": 44
    },
    "status": "OK"
  },
  "part": "Engine",
  "time": 1571321256415,
  "meth": "takeDecision"
},{
  "data": {"action": "fly"},
  "part": "Explorer",
  "time": 1571321256415,
  "meth": "takeDecision"
},{
  "data": {
    "cost": 2,
    "extras": {},
    "status": "OK"
  },
  "part": "Engine",
  "time": 1571321256415,
  "meth": "takeDecision"
},{
  "data": {
    "action": "echo",
    "parameters": {"direction": "E"}
  },
  "part": "Explorer",
  "time": 1571321256415,
  "meth": "takeDecision"
},{
  "data": {
    "cost": 5,
    "extras": {
      "found": "OUT_OF_RANGE",
      "range": 8
    },
    "status": "OK"
  },
  "part": "Engine",
  "time": 1571321256415,
  "meth": "takeDecision"
},{
  "data": {
    "action": "echo",
    "parameters": {"direction": "W"}
  },
  "part": "Explorer",
  "time": 1571321256415,
  "meth": "takeDecision"
},{
  "data": {
    "cost": 3,
    "extras": {
      "found": "OUT_OF_RANGE",
      "range": 44
    },
    "status": "OK"
  },
  "part": "Engine",
  "time": 1571321256416,
  "meth": "takeDecision"
},{
  "data": {"action": "fly"},
  "part": "Explorer",
  "time": 1571321256416,
  "meth": "takeDecision"
},{
  "data": {
    "cost": 3,
    "extras": {},
    "status": "OK"
  },
  "part": "Engine",
  "time": 1571321256416,
  "meth": "takeDecision"
},{
  "data": {
    "action": "echo",
    "parameters": {"direction": "E"}
  },
  "part": "Explorer",
  "time": 1571321256416,
  "meth": "takeDecision"
},{
  "data": {
    "cost": 5,
    "extras": {
      "found": "OUT_OF_RANGE",
      "range": 8
    },
    "status": "OK"
  },
  "part": "Engine",
  "time": 1571321256416,
  "meth": "takeDecision"
},{
  "data": {
    "action": "echo",
    "parameters": {"direction": "W"}
  },
  "part": "Explorer",
  "time": 1571321256416,
  "meth": "takeDecision"
},{
  "data": {
    "cost": 6,
    "extras": {
      "found": "OUT_OF_RANGE",
      "range": 44
    },
    "status": "OK"
  },
  "part": "Engine",
  "time": 1571321256416,
  "meth": "takeDecision"
},{
  "data": {"action": "fly"},
  "part": "Explorer",
  "time": 1571321256416,
  "meth": "takeDecision"
},{
  "data": {
    "cost": 3,
    "extras": {},
    "status": "OK"
  },
  "part": "Engine",
  "time": 1571321256416,
  "meth": "takeDecision"
},{
  "data": {
    "action": "echo",
    "parameters": {"direction": "E"}
  },
  "part": "Explorer",
  "time": 1571321256416,
  "meth": "takeDecision"
},{
  "data": {
    "cost": 5,
    "extras": {
      "found": "OUT_OF_RANGE",
      "range": 8
    },
    "status": "OK"
  },
  "part": "Engine",
  "time": 1571321256416,
  "meth": "takeDecision"
},{
  "data": {
    "action": "echo",
    "parameters": {"direction": "W"}
  },
  "part": "Explorer",
  "time": 1571321256416,
  "meth": "takeDecision"
},{
  "data": {
    "cost": 7,
    "extras": {
      "found": "GROUND",
      "range": 16
    },
    "status": "OK"
  },
  "part": "Engine",
  "time": 1571321256417,
  "meth": "takeDecision"
},{
  "data": {"action": "fly"},
  "part": "Explorer",
  "time": 1571321256417,
  "meth": "takeDecision"
},{
  "data": {
    "cost": 5,
    "extras": {},
    "status": "OK"
  },
  "part": "Engine",
  "time": 1571321256417,
  "meth": "takeDecision"
},{
  "data": {
    "action": "echo",
    "parameters": {"direction": "E"}
  },
  "part": "Explorer",
  "time": 1571321256417,
  "meth": "takeDecision"
},{
  "data": {
    "cost": 6,
    "extras": {
      "found": "OUT_OF_RANGE",
      "range": 8
    },
    "status": "OK"
  },
  "part": "Engine",
  "time": 1571321256417,
  "meth": "takeDecision"
},{
  "data": {
    "action": "echo",
    "parameters": {"direction": "W"}
  },
  "part": "Explorer",
  "time": 1571321256417,
  "meth": "takeDecision"
},{
  "data": {
    "cost": 5,
    "extras": {
      "found": "GROUND",
      "range": 13
    },
    "status": "OK"
  },
  "part": "Engine",
  "time": 1571321256417,
  "meth": "takeDecision"
},{
  "data": {"action": "fly"},
  "part": "Explorer",
  "time": 1571321256417,
  "meth": "takeDecision"
},{
  "data": {
    "cost": 3,
    "extras": {},
    "status": "OK"
  },
  "part": "Engine",
  "time": 1571321256417,
  "meth": "takeDecision"
},{
  "data": {
    "action": "echo",
    "parameters": {"direction": "E"}
  },
  "part": "Explorer",
  "time": 1571321256417,
  "meth": "takeDecision"
},{
  "data": {
    "cost": 7,
    "extras": {
      "found": "OUT_OF_RANGE",
      "range": 8
    },
    "status": "OK"
  },
  "part": "Engine",
  "time": 1571321256417,
  "meth": "takeDecision"
},{
  "data": {
    "action": "echo",
    "parameters": {"direction": "W"}
  },
  "part": "Explorer",
  "time": 1571321256417,
  "meth": "takeDecision"
},{
  "data": {
    "cost": 3,
    "extras": {
      "found": "GROUND",
      "range": 10
    },
    "status": "OK"
  },
  "part": "Engine",
  "time": 1571321256417,
  "meth": "takeDecision"
},{
  "data": {"action": "fly"},
  "part": "Explorer",
  "time": 1571321256417,
  "meth": "takeDecision"
},{
  "data": {
    "cost": 4,
    "extras": {},
    "status": "OK"
  },
  "part": "Engine",
  "time": 1571321256417,
  "meth": "takeDecision"
},{
  "data": {
    "action": "echo",
    "parameters": {"direction": "E"}
  },
  "part": "Explorer",
  "time": 1571321256417,
  "meth": "takeDecision"
},{
  "data": {
    "cost": 5,
    "extras": {
      "found": "OUT_OF_RANGE",
      "range": 8
    },
    "status": "OK"
  },
  "part": "Engine",
  "time": 1571321256418,
  "meth": "takeDecision"
},{
  "data": {
    "action": "echo",
    "parameters": {"direction": "W"}
  },
  "part": "Explorer",
  "time": 1571321256418,
  "meth": "takeDecision"
},{
  "data": {
    "cost": 3,
    "extras": {
      "found": "GROUND",
      "range": 9
    },
    "status": "OK"
  },
  "part": "Engine",
  "time": 1571321256418,
  "meth": "takeDecision"
},{
  "data": {"action": "fly"},
  "part": "Explorer",
  "time": 1571321256418,
  "meth": "takeDecision"
},{
  "data": {
    "cost": 4,
    "extras": {},
    "status": "OK"
  },
  "part": "Engine",
  "time": 1571321256418,
  "meth": "takeDecision"
},{
  "data": {
    "action": "echo",
    "parameters": {"direction": "E"}
  },
  "part": "Explorer",
  "time": 1571321256418,
  "meth": "takeDecision"
},{
  "data": {
    "cost": 6,
    "extras": {
      "found": "OUT_OF_RANGE",
      "range": 8
    },
    "status": "OK"
  },
  "part": "Engine",
  "time": 1571321256418,
  "meth": "takeDecision"
},{
  "data": {
    "action": "echo",
    "parameters": {"direction": "W"}
  },
  "part": "Explorer",
  "time": 1571321256418,
  "meth": "takeDecision"
},{
  "data": {
    "cost": 6,
    "extras": {
      "found": "GROUND",
      "range": 8
    },
    "status": "OK"
  },
  "part": "Engine",
  "time": 1571321256418,
  "meth": "takeDecision"
},{
  "data": {"action": "fly"},
  "part": "Explorer",
  "time": 1571321256418,
  "meth": "takeDecision"
},{
  "data": {
    "cost": 3,
    "extras": {},
    "status": "OK"
  },
  "part": "Engine",
  "time": 1571321256418,
  "meth": "takeDecision"
},{
  "data": {
    "action": "echo",
    "parameters": {"direction": "E"}
  },
  "part": "Explorer",
  "time": 1571321256418,
  "meth": "takeDecision"
},{
  "data": {
    "cost": 3,
    "extras": {
      "found": "OUT_OF_RANGE",
      "range": 8
    },
    "status": "OK"
  },
  "part": "Engine",
  "time": 1571321256418,
  "meth": "takeDecision"
},{
  "data": {
    "action": "echo",
    "parameters": {"direction": "W"}
  },
  "part": "Explorer",
  "time": 1571321256418,
  "meth": "takeDecision"
},{
  "data": {
    "cost": 3,
    "extras": {
      "found": "GROUND",
      "range": 6
    },
    "status": "OK"
  },
  "part": "Engine",
  "time": 1571321256418,
  "meth": "takeDecision"
},{
  "data": {"action": "fly"},
  "part": "Explorer",
  "time": 1571321256418,
  "meth": "takeDecision"
},{
  "data": {
    "cost": 2,
    "extras": {},
    "status": "OK"
  },
  "part": "Engine",
  "time": 1571321256418,
  "meth": "takeDecision"
},{
  "data": {
    "action": "echo",
    "parameters": {"direction": "E"}
  },
  "part": "Explorer",
  "time": 1571321256418,
  "meth": "takeDecision"
},{
  "data": {
    "cost": 5,
    "extras": {
      "found": "OUT_OF_RANGE",
      "range": 8
    },
    "status": "OK"
  },
  "part": "Engine",
  "time": 1571321256418,
  "meth": "takeDecision"
},{
  "data": {
    "action": "echo",
    "parameters": {"direction": "W"}
  },
  "part": "Explorer",
  "time": 1571321256418,
  "meth": "takeDecision"
},{
  "data": {
    "cost": 5,
    "extras": {
      "found": "GROUND",
      "range": 5
    },
    "status": "OK"
  },
  "part": "Engine",
  "time": 1571321256418,
  "meth": "takeDecision"
},{
  "data": {"action": "fly"},
  "part": "Explorer",
  "time": 1571321256419,
  "meth": "takeDecision"
},{
  "data": {
    "cost": 3,
    "extras": {},
    "status": "OK"
  },
  "part": "Engine",
  "time": 1571321256419,
  "meth": "takeDecision"
},{
  "data": {
    "action": "echo",
    "parameters": {"direction": "E"}
  },
  "part": "Explorer",
  "time": 1571321256419,
  "meth": "takeDecision"
},{
  "data": {
    "cost": 5,
    "extras": {
      "found": "OUT_OF_RANGE",
      "range": 8
    },
    "status": "OK"
  },
  "part": "Engine",
  "time": 1571321256419,
  "meth": "takeDecision"
},{
  "data": {
    "action": "echo",
    "parameters": {"direction": "W"}
  },
  "part": "Explorer",
  "time": 1571321256419,
  "meth": "takeDecision"
},{
  "data": {
    "cost": 6,
    "extras": {
      "found": "GROUND",
      "range": 5
    },
    "status": "OK"
  },
  "part": "Engine",
  "time": 1571321256419,
  "meth": "takeDecision"
},{
  "data": {"action": "fly"},
  "part": "Explorer",
  "time": 1571321256419,
  "meth": "takeDecision"
},{
  "data": {
    "cost": 2,
    "extras": {},
    "status": "OK"
  },
  "part": "Engine",
  "time": 1571321256419,
  "meth": "takeDecision"
},{
  "data": {
    "action": "echo",
    "parameters": {"direction": "E"}
  },
  "part": "Explorer",
  "time": 1571321256419,
  "meth": "takeDecision"
},{
  "data": {
    "cost": 7,
    "extras": {
      "found": "OUT_OF_RANGE",
      "range": 8
    },
    "status": "OK"
  },
  "part": "Engine",
  "time": 1571321256419,
  "meth": "takeDecision"
},{
  "data": {
    "action": "echo",
    "parameters": {"direction": "W"}
  },
  "part": "Explorer",
  "time": 1571321256419,
  "meth": "takeDecision"
},{
  "data": {
    "cost": 4,
    "extras": {
      "found": "GROUND",
      "range": 4
    },
    "status": "OK"
  },
  "part": "Engine",
  "time": 1571321256419,
  "meth": "takeDecision"
},{
  "data": {"action": "fly"},
  "part": "Explorer",
  "time": 1571321256419,
  "meth": "takeDecision"
},{
  "data": {
    "cost": 5,
    "extras": {},
    "status": "OK"
  },
  "part": "Engine",
  "time": 1571321256419,
  "meth": "takeDecision"
},{
  "data": {
    "action": "echo",
    "parameters": {"direction": "E"}
  },
  "part": "Explorer",
  "time": 1571321256419,
  "meth": "takeDecision"
},{
  "data": {
    "cost": 4,
    "extras": {
      "found": "OUT_OF_RANGE",
      "range": 8
    },
    "status": "OK"
  },
  "part": "Engine",
  "time": 1571321256419,
  "meth": "takeDecision"
},{
  "data": {
    "action": "echo",
    "parameters": {"direction": "W"}
  },
  "part": "Explorer",
  "time": 1571321256419,
  "meth": "takeDecision"
},{
  "data": {
    "cost": 5,
    "extras": {
      "found": "GROUND",
      "range": 3
    },
    "status": "OK"
  },
  "part": "Engine",
  "time": 1571321256419,
  "meth": "takeDecision"
},{
  "data": {"action": "fly"},
  "part": "Explorer",
  "time": 1571321256419,
  "meth": "takeDecision"
},{
  "data": {
    "cost": 3,
    "extras": {},
    "status": "OK"
  },
  "part": "Engine",
  "time": 1571321256419,
  "meth": "takeDecision"
},{
  "data": {
    "action": "echo",
    "parameters": {"direction": "E"}
  },
  "part": "Explorer",
  "time": 1571321256419,
  "meth": "takeDecision"
},{
  "data": {
    "cost": 6,
    "extras": {
      "found": "OUT_OF_RANGE",
      "range": 8
    },
    "status": "OK"
  },
  "part": "Engine",
  "time": 1571321256420,
  "meth": "takeDecision"
},{
  "data": {
    "action": "echo",
    "parameters": {"direction": "W"}
  },
  "part": "Explorer",
  "time": 1571321256420,
  "meth": "takeDecision"
},{
  "data": {
    "cost": 6,
    "extras": {
      "found": "GROUND",
      "range": 3
    },
    "status": "OK"
  },
  "part": "Engine",
  "time": 1571321256420,
  "meth": "takeDecision"
},{
  "data": {"action": "fly"},
  "part": "Explorer",
  "time": 1571321256420,
  "meth": "takeDecision"
},{
  "data": {
    "cost": 2,
    "extras": {},
    "status": "OK"
  },
  "part": "Engine",
  "time": 1571321256420,
  "meth": "takeDecision"
},{
  "data": {
    "action": "echo",
    "parameters": {"direction": "E"}
  },
  "part": "Explorer",
  "time": 1571321256420,
  "meth": "takeDecision"
},{
  "data": {
    "cost": 6,
    "extras": {
      "found": "OUT_OF_RANGE",
      "range": 8
    },
    "status": "OK"
  },
  "part": "Engine",
  "time": 1571321256420,
  "meth": "takeDecision"
},{
  "data": {
    "action": "echo",
    "parameters": {"direction": "W"}
  },
  "part": "Explorer",
  "time": 1571321256420,
  "meth": "takeDecision"
},{
  "data": {
    "cost": 5,
    "extras": {
      "found": "GROUND",
      "range": 3
    },
    "status": "OK"
  },
  "part": "Engine",
  "time": 1571321256420,
  "meth": "takeDecision"
},{
  "data": {"action": "fly"},
  "part": "Explorer",
  "time": 1571321256420,
  "meth": "takeDecision"
},{
  "data": {
    "cost": 3,
    "extras": {},
    "status": "OK"
  },
  "part": "Engine",
  "time": 1571321256420,
  "meth": "takeDecision"
},{
  "data": {
    "action": "echo",
    "parameters": {"direction": "E"}
  },
  "part": "Explorer",
  "time": 1571321256420,
  "meth": "takeDecision"
},{
  "data": {
    "cost": 4,
    "extras": {
      "found": "OUT_OF_RANGE",
      "range": 8
    },
    "status": "OK"
  },
  "part": "Engine",
  "time": 1571321256420,
  "meth": "takeDecision"
},{
  "data": {
    "action": "echo",
    "parameters": {"direction": "W"}
  },
  "part": "Explorer",
  "time": 1571321256420,
  "meth": "takeDecision"
},{
  "data": {
    "cost": 4,
    "extras": {
      "found": "GROUND",
      "range": 2
    },
    "status": "OK"
  },
  "part": "Engine",
  "time": 1571321256420,
  "meth": "takeDecision"
},{
  "data": {"action": "fly"},
  "part": "Explorer",
  "time": 1571321256420,
  "meth": "takeDecision"
},{
  "data": {
    "cost": 4,
    "extras": {},
    "status": "OK"
  },
  "part": "Engine",
  "time": 1571321256420,
  "meth": "takeDecision"
},{
  "data": {
    "action": "echo",
    "parameters": {"direction": "E"}
  },
  "part": "Explorer",
  "time": 1571321256420,
  "meth": "takeDecision"
},{
  "data": {
    "cost": 6,
    "extras": {
      "found": "OUT_OF_RANGE",
      "range": 8
    },
    "status": "OK"
  },
  "part": "Engine",
  "time": 1571321256420,
  "meth": "takeDecision"
},{
  "data": {
    "action": "echo",
    "parameters": {"direction": "W"}
  },
  "part": "Explorer",
  "time": 1571321256420,
  "meth": "takeDecision"
},{
  "data": {
    "cost": 5,
    "extras": {
      "found": "GROUND",
      "range": 2
    },
    "status": "OK"
  },
  "part": "Engine",
  "time": 1571321256420,
  "meth": "takeDecision"
},{
  "data": {"action": "fly"},
  "part": "Explorer",
  "time": 1571321256420,
  "meth": "takeDecision"
},{
  "data": {
    "cost": 5,
    "extras": {},
    "status": "OK"
  },
  "part": "Engine",
  "time": 1571321256421,
  "meth": "takeDecision"
},{
  "data": {
    "action": "echo",
    "parameters": {"direction": "E"}
  },
  "part": "Explorer",
  "time": 1571321256421,
  "meth": "takeDecision"
},{
  "data": {
    "cost": 3,
    "extras": {
      "found": "OUT_OF_RANGE",
      "range": 8
    },
    "status": "OK"
  },
  "part": "Engine",
  "time": 1571321256421,
  "meth": "takeDecision"
},{
  "data": {
    "action": "echo",
    "parameters": {"direction": "W"}
  },
  "part": "Explorer",
  "time": 1571321256421,
  "meth": "takeDecision"
},{
  "data": {
    "cost": 4,
    "extras": {
      "found": "GROUND",
      "range": 2
    },
    "status": "OK"
  },
  "part": "Engine",
  "time": 1571321256421,
  "meth": "takeDecision"
},{
  "data": {"action": "fly"},
  "part": "Explorer",
  "time": 1571321256421,
  "meth": "takeDecision"
},{
  "data": {
    "cost": 3,
    "extras": {},
    "status": "OK"
  },
  "part": "Engine",
  "time": 1571321256421,
  "meth": "takeDecision"
},{
  "data": {
    "action": "echo",
    "parameters": {"direction": "E"}
  },
  "part": "Explorer",
  "time": 1571321256421,
  "meth": "takeDecision"
},{
  "data": {
    "cost": 5,
    "extras": {
      "found": "OUT_OF_RANGE",
      "range": 8
    },
    "status": "OK"
  },
  "part": "Engine",
  "time": 1571321256421,
  "meth": "takeDecision"
},{
  "data": {
    "action": "echo",
    "parameters": {"direction": "W"}
  },
  "part": "Explorer",
  "time": 1571321256421,
  "meth": "takeDecision"
},{
  "data": {
    "cost": 6,
    "extras": {
      "found": "GROUND",
      "range": 2
    },
    "status": "OK"
  },
  "part": "Engine",
  "time": 1571321256421,
  "meth": "takeDecision"
},{
  "data": {"action": "fly"},
  "part": "Explorer",
  "time": 1571321256421,
  "meth": "takeDecision"
},{
  "data": {
    "cost": 4,
    "extras": {},
    "status": "OK"
  },
  "part": "Engine",
  "time": 1571321256421,
  "meth": "takeDecision"
},{
  "data": {
    "action": "echo",
    "parameters": {"direction": "E"}
  },
  "part": "Explorer",
  "time": 1571321256421,
  "meth": "takeDecision"
},{
  "data": {
    "cost": 6,
    "extras": {
      "found": "OUT_OF_RANGE",
      "range": 8
    },
    "status": "OK"
  },
  "part": "Engine",
  "time": 1571321256421,
  "meth": "takeDecision"
},{
  "data": {
    "action": "echo",
    "parameters": {"direction": "W"}
  },
  "part": "Explorer",
  "time": 1571321256421,
  "meth": "takeDecision"
},{
  "data": {
    "cost": 4,
    "extras": {
      "found": "GROUND",
      "range": 2
    },
    "status": "OK"
  },
  "part": "Engine",
  "time": 1571321256421,
  "meth": "takeDecision"
},{
  "data": {"action": "fly"},
  "part": "Explorer",
  "time": 1571321256421,
  "meth": "takeDecision"
},{
  "data": {
    "cost": 3,
    "extras": {},
    "status": "OK"
  },
  "part": "Engine",
  "time": 1571321256421,
  "meth": "takeDecision"
},{
  "data": {
    "action": "echo",
    "parameters": {"direction": "E"}
  },
  "part": "Explorer",
  "time": 1571321256421,
  "meth": "takeDecision"
},{
  "data": {
    "cost": 3,
    "extras": {
      "found": "OUT_OF_RANGE",
      "range": 8
    },
    "status": "OK"
  },
  "part": "Engine",
  "time": 1571321256422,
  "meth": "takeDecision"
},{
  "data": {
    "action": "echo",
    "parameters": {"direction": "W"}
  },
  "part": "Explorer",
  "time": 1571321256422,
  "meth": "takeDecision"
},{
  "data": {
    "cost": 5,
    "extras": {
      "found": "GROUND",
      "range": 1
    },
    "status": "OK"
  },
  "part": "Engine",
  "time": 1571321256422,
  "meth": "takeDecision"
},{
  "data": {"action": "fly"},
  "part": "Explorer",
  "time": 1571321256422,
  "meth": "takeDecision"
},{
  "data": {
    "cost": 3,
    "extras": {},
    "status": "OK"
  },
  "part": "Engine",
  "time": 1571321256422,
  "meth": "takeDecision"
},{
  "data": {
    "action": "echo",
    "parameters": {"direction": "E"}
  },
  "part": "Explorer",
  "time": 1571321256422,
  "meth": "takeDecision"
},{
  "data": {
    "cost": 5,
    "extras": {
      "found": "OUT_OF_RANGE",
      "range": 8
    },
    "status": "OK"
  },
  "part": "Engine",
  "time": 1571321256422,
  "meth": "takeDecision"
},{
  "data": {
    "action": "echo",
    "parameters": {"direction": "W"}
  },
  "part": "Explorer",
  "time": 1571321256422,
  "meth": "takeDecision"
},{
  "data": {
    "cost": 5,
    "extras": {
      "found": "GROUND",
      "range": 1
    },
    "status": "OK"
  },
  "part": "Engine",
  "time": 1571321256422,
  "meth": "takeDecision"
},{
  "data": {"action": "fly"},
  "part": "Explorer",
  "time": 1571321256422,
  "meth": "takeDecision"
},{
  "data": {
    "cost": 5,
    "extras": {},
    "status": "OK"
  },
  "part": "Engine",
  "time": 1571321256422,
  "meth": "takeDecision"
},{
  "data": {
    "action": "echo",
    "parameters": {"direction": "E"}
  },
  "part": "Explorer",
  "time": 1571321256422,
  "meth": "takeDecision"
},{
  "data": {
    "cost": 4,
    "extras": {
      "found": "OUT_OF_RANGE",
      "range": 8
    },
    "status": "OK"
  },
  "part": "Engine",
  "time": 1571321256422,
  "meth": "takeDecision"
},{
  "data": {
    "action": "echo",
    "parameters": {"direction": "W"}
  },
  "part": "Explorer",
  "time": 1571321256422,
  "meth": "takeDecision"
},{
  "data": {
    "cost": 5,
    "extras": {
      "found": "GROUND",
      "range": 2
    },
    "status": "OK"
  },
  "part": "Engine",
  "time": 1571321256422,
  "meth": "takeDecision"
},{
  "data": {"action": "fly"},
  "part": "Explorer",
  "time": 1571321256422,
  "meth": "takeDecision"
},{
  "data": {
    "cost": 2,
    "extras": {},
    "status": "OK"
  },
  "part": "Engine",
  "time": 1571321256422,
  "meth": "takeDecision"
},{
  "data": {
    "action": "echo",
    "parameters": {"direction": "E"}
  },
  "part": "Explorer",
  "time": 1571321256422,
  "meth": "takeDecision"
},{
  "data": {
    "cost": 5,
    "extras": {
      "found": "OUT_OF_RANGE",
      "range": 8
    },
    "status": "OK"
  },
  "part": "Engine",
  "time": 1571321256422,
  "meth": "takeDecision"
},{
  "data": {
    "action": "echo",
    "parameters": {"direction": "W"}
  },
  "part": "Explorer",
  "time": 1571321256422,
  "meth": "takeDecision"
},{
  "data": {
    "cost": 4,
    "extras": {
      "found": "GROUND",
      "range": 2
    },
    "status": "OK"
  },
  "part": "Engine",
  "time": 1571321256423,
  "meth": "takeDecision"
},{
  "data": {"action": "fly"},
  "part": "Explorer",
  "time": 1571321256423,
  "meth": "takeDecision"
},{
  "data": {
    "cost": 3,
    "extras": {},
    "status": "OK"
  },
  "part": "Engine",
  "time": 1571321256423,
  "meth": "takeDecision"
},{
  "data": {
    "action": "echo",
    "parameters": {"direction": "E"}
  },
  "part": "Explorer",
  "time": 1571321256423,
  "meth": "takeDecision"
},{
  "data": {
    "cost": 4,
    "extras": {
      "found": "OUT_OF_RANGE",
      "range": 8
    },
    "status": "OK"
  },
  "part": "Engine",
  "time": 1571321256423,
  "meth": "takeDecision"
},{
  "data": {
    "action": "echo",
    "parameters": {"direction": "W"}
  },
  "part": "Explorer",
  "time": 1571321256423,
  "meth": "takeDecision"
},{
  "data": {
    "cost": 6,
    "extras": {
      "found": "GROUND",
      "range": 2
    },
    "status": "OK"
  },
  "part": "Engine",
  "time": 1571321256423,
  "meth": "takeDecision"
},{
  "data": {"action": "fly"},
  "part": "Explorer",
  "time": 1571321256423,
  "meth": "takeDecision"
},{
  "data": {
    "cost": 2,
    "extras": {},
    "status": "OK"
  },
  "part": "Engine",
  "time": 1571321256423,
  "meth": "takeDecision"
},{
  "data": {
    "action": "echo",
    "parameters": {"direction": "E"}
  },
  "part": "Explorer",
  "time": 1571321256423,
  "meth": "takeDecision"
},{
  "data": {
    "cost": 4,
    "extras": {
      "found": "OUT_OF_RANGE",
      "range": 8
    },
    "status": "OK"
  },
  "part": "Engine",
  "time": 1571321256423,
  "meth": "takeDecision"
},{
  "data": {
    "action": "echo",
    "parameters": {"direction": "W"}
  },
  "part": "Explorer",
  "time": 1571321256423,
  "meth": "takeDecision"
},{
  "data": {
    "cost": 5,
    "extras": {
      "found": "GROUND",
      "range": 3
    },
    "status": "OK"
  },
  "part": "Engine",
  "time": 1571321256423,
  "meth": "takeDecision"
},{
  "data": {"action": "fly"},
  "part": "Explorer",
  "time": 1571321256423,
  "meth": "takeDecision"
},{
  "data": {
    "cost": 3,
    "extras": {},
    "status": "OK"
  },
  "part": "Engine",
  "time": 1571321256423,
  "meth": "takeDecision"
},{
  "data": {
    "action": "echo",
    "parameters": {"direction": "E"}
  },
  "part": "Explorer",
  "time": 1571321256423,
  "meth": "takeDecision"
},{
  "data": {
    "cost": 6,
    "extras": {
      "found": "OUT_OF_RANGE",
      "range": 8
    },
    "status": "OK"
  },
  "part": "Engine",
  "time": 1571321256423,
  "meth": "takeDecision"
},{
  "data": {
    "action": "echo",
    "parameters": {"direction": "W"}
  },
  "part": "Explorer",
  "time": 1571321256423,
  "meth": "takeDecision"
},{
  "data": {
    "cost": 4,
    "extras": {
      "found": "GROUND",
      "range": 4
    },
    "status": "OK"
  },
  "part": "Engine",
  "time": 1571321256423,
  "meth": "takeDecision"
},{
  "data": {"action": "fly"},
  "part": "Explorer",
  "time": 1571321256423,
  "meth": "takeDecision"
},{
  "data": {
    "cost": 4,
    "extras": {},
    "status": "OK"
  },
  "part": "Engine",
  "time": 1571321256423,
  "meth": "takeDecision"
},{
  "data": {
    "action": "echo",
    "parameters": {"direction": "E"}
  },
  "part": "Explorer",
  "time": 1571321256423,
  "meth": "takeDecision"
},{
  "data": {
    "cost": 3,
    "extras": {
      "found": "OUT_OF_RANGE",
      "range": 8
    },
    "status": "OK"
  },
  "part": "Engine",
  "time": 1571321256424,
  "meth": "takeDecision"
},{
  "data": {
    "action": "echo",
    "parameters": {"direction": "W"}
  },
  "part": "Explorer",
  "time": 1571321256424,
  "meth": "takeDecision"
},{
  "data": {
    "cost": 5,
    "extras": {
      "found": "GROUND",
      "range": 4
    },
    "status": "OK"
  },
  "part": "Engine",
  "time": 1571321256424,
  "meth": "takeDecision"
},{
  "data": {"action": "fly"},
  "part": "Explorer",
  "time": 1571321256424,
  "meth": "takeDecision"
},{
  "data": {
    "cost": 3,
    "extras": {},
    "status": "OK"
  },
  "part": "Engine",
  "time": 1571321256424,
  "meth": "takeDecision"
},{
  "data": {
    "action": "echo",
    "parameters": {"direction": "E"}
  },
  "part": "Explorer",
  "time": 1571321256424,
  "meth": "takeDecision"
},{
  "data": {
    "cost": 5,
    "extras": {
      "found": "OUT_OF_RANGE",
      "range": 8
    },
    "status": "OK"
  },
  "part": "Engine",
  "time": 1571321256424,
  "meth": "takeDecision"
},{
  "data": {
    "action": "echo",
    "parameters": {"direction": "W"}
  },
  "part": "Explorer",
  "time": 1571321256424,
  "meth": "takeDecision"
},{
  "data": {
    "cost": 4,
    "extras": {
      "found": "GROUND",
      "range": 5
    },
    "status": "OK"
  },
  "part": "Engine",
  "time": 1571321256424,
  "meth": "takeDecision"
},{
  "data": {"action": "fly"},
  "part": "Explorer",
  "time": 1571321256424,
  "meth": "takeDecision"
},{
  "data": {
    "cost": 5,
    "extras": {},
    "status": "OK"
  },
  "part": "Engine",
  "time": 1571321256424,
  "meth": "takeDecision"
},{
  "data": {
    "action": "echo",
    "parameters": {"direction": "E"}
  },
  "part": "Explorer",
  "time": 1571321256424,
  "meth": "takeDecision"
},{
  "data": {
    "cost": 5,
    "extras": {
      "found": "OUT_OF_RANGE",
      "range": 8
    },
    "status": "OK"
  },
  "part": "Engine",
  "time": 1571321256424,
  "meth": "takeDecision"
},{
  "data": {
    "action": "echo",
    "parameters": {"direction": "W"}
  },
  "part": "Explorer",
  "time": 1571321256424,
  "meth": "takeDecision"
},{
  "data": {
    "cost": 3,
    "extras": {
      "found": "GROUND",
      "range": 5
    },
    "status": "OK"
  },
  "part": "Engine",
  "time": 1571321256424,
  "meth": "takeDecision"
},{
  "data": {"action": "fly"},
  "part": "Explorer",
  "time": 1571321256424,
  "meth": "takeDecision"
},{
  "data": {
    "cost": 4,
    "extras": {},
    "status": "OK"
  },
  "part": "Engine",
  "time": 1571321256424,
  "meth": "takeDecision"
},{
  "data": {
    "action": "echo",
    "parameters": {"direction": "E"}
  },
  "part": "Explorer",
  "time": 1571321256424,
  "meth": "takeDecision"
},{
  "data": {
    "cost": 4,
    "extras": {
      "found": "OUT_OF_RANGE",
      "range": 8
    },
    "status": "OK"
  },
  "part": "Engine",
  "time": 1571321256424,
  "meth": "takeDecision"
},{
  "data": {
    "action": "echo",
    "parameters": {"direction": "W"}
  },
  "part": "Explorer",
  "time": 1571321256424,
  "meth": "takeDecision"
},{
  "data": {
    "cost": 6,
    "extras": {
      "found": "GROUND",
      "range": 6
    },
    "status": "OK"
  },
  "part": "Engine",
  "time": 1571321256424,
  "meth": "takeDecision"
},{
  "data": {"action": "fly"},
  "part": "Explorer",
  "time": 1571321256425,
  "meth": "takeDecision"
},{
  "data": {
    "cost": 2,
    "extras": {},
    "status": "OK"
  },
  "part": "Engine",
  "time": 1571321256425,
  "meth": "takeDecision"
},{
  "data": {
    "action": "echo",
    "parameters": {"direction": "E"}
  },
  "part": "Explorer",
  "time": 1571321256425,
  "meth": "takeDecision"
},{
  "data": {
    "cost": 6,
    "extras": {
      "found": "OUT_OF_RANGE",
      "range": 8
    },
    "status": "OK"
  },
  "part": "Engine",
  "time": 1571321256425,
  "meth": "takeDecision"
},{
  "data": {
    "action": "echo",
    "parameters": {"direction": "W"}
  },
  "part": "Explorer",
  "time": 1571321256425,
  "meth": "takeDecision"
},{
  "data": {
    "cost": 6,
    "extras": {
      "found": "GROUND",
      "range": 7
    },
    "status": "OK"
  },
  "part": "Engine",
  "time": 1571321256425,
  "meth": "takeDecision"
},{
  "data": {"action": "fly"},
  "part": "Explorer",
  "time": 1571321256425,
  "meth": "takeDecision"
},{
  "data": {
    "cost": 5,
    "extras": {},
    "status": "OK"
  },
  "part": "Engine",
  "time": 1571321256425,
  "meth": "takeDecision"
},{
  "data": {
    "action": "echo",
    "parameters": {"direction": "E"}
  },
  "part": "Explorer",
  "time": 1571321256425,
  "meth": "takeDecision"
},{
  "data": {
    "cost": 3,
    "extras": {
      "found": "OUT_OF_RANGE",
      "range": 8
    },
    "status": "OK"
  },
  "part": "Engine",
  "time": 1571321256425,
  "meth": "takeDecision"
},{
  "data": {
    "action": "echo",
    "parameters": {"direction": "W"}
  },
  "part": "Explorer",
  "time": 1571321256425,
  "meth": "takeDecision"
},{
  "data": {
    "cost": 6,
    "extras": {
      "found": "GROUND",
      "range": 8
    },
    "status": "OK"
  },
  "part": "Engine",
  "time": 1571321256425,
  "meth": "takeDecision"
},{
  "data": {"action": "fly"},
  "part": "Explorer",
  "time": 1571321256425,
  "meth": "takeDecision"
},{
  "data": {
    "cost": 3,
    "extras": {},
    "status": "OK"
  },
  "part": "Engine",
  "time": 1571321256425,
  "meth": "takeDecision"
},{
  "data": {
    "action": "echo",
    "parameters": {"direction": "E"}
  },
  "part": "Explorer",
  "time": 1571321256425,
  "meth": "takeDecision"
},{
  "data": {
    "cost": 6,
    "extras": {
      "found": "OUT_OF_RANGE",
      "range": 8
    },
    "status": "OK"
  },
  "part": "Engine",
  "time": 1571321256425,
  "meth": "takeDecision"
},{
  "data": {
    "action": "echo",
    "parameters": {"direction": "W"}
  },
  "part": "Explorer",
  "time": 1571321256425,
  "meth": "takeDecision"
},{
  "data": {
    "cost": 5,
    "extras": {
      "found": "GROUND",
      "range": 9
    },
    "status": "OK"
  },
  "part": "Engine",
  "time": 1571321256425,
  "meth": "takeDecision"
},{
  "data": {"action": "fly"},
  "part": "Explorer",
  "time": 1571321256426,
  "meth": "takeDecision"
},{
  "data": {
    "cost": 3,
    "extras": {},
    "status": "OK"
  },
  "part": "Engine",
  "time": 1571321256426,
  "meth": "takeDecision"
},{
  "data": {
    "action": "echo",
    "parameters": {"direction": "E"}
  },
  "part": "Explorer",
  "time": 1571321256426,
  "meth": "takeDecision"
},{
  "data": {
    "cost": 4,
    "extras": {
      "found": "OUT_OF_RANGE",
      "range": 8
    },
    "status": "OK"
  },
  "part": "Engine",
  "time": 1571321256426,
  "meth": "takeDecision"
},{
  "data": {
    "action": "echo",
    "parameters": {"direction": "W"}
  },
  "part": "Explorer",
  "time": 1571321256426,
  "meth": "takeDecision"
},{
  "data": {
    "cost": 5,
    "extras": {
      "found": "GROUND",
      "range": 12
    },
    "status": "OK"
  },
  "part": "Engine",
  "time": 1571321256426,
  "meth": "takeDecision"
},{
  "data": {"action": "fly"},
  "part": "Explorer",
  "time": 1571321256426,
  "meth": "takeDecision"
},{
  "data": {
    "cost": 4,
    "extras": {},
    "status": "OK"
  },
  "part": "Engine",
  "time": 1571321256426,
  "meth": "takeDecision"
},{
  "data": {
    "action": "echo",
    "parameters": {"direction": "E"}
  },
  "part": "Explorer",
  "time": 1571321256426,
  "meth": "takeDecision"
},{
  "data": {
    "cost": 5,
    "extras": {
      "found": "OUT_OF_RANGE",
      "range": 8
    },
    "status": "OK"
  },
  "part": "Engine",
  "time": 1571321256426,
  "meth": "takeDecision"
},{
  "data": {
    "action": "echo",
    "parameters": {"direction": "W"}
  },
  "part": "Explorer",
  "time": 1571321256426,
  "meth": "takeDecision"
},{
  "data": {
    "cost": 5,
    "extras": {
      "found": "GROUND",
      "range": 16
    },
    "status": "OK"
  },
  "part": "Engine",
  "time": 1571321256426,
  "meth": "takeDecision"
},{
  "data": {"action": "fly"},
  "part": "Explorer",
  "time": 1571321256426,
  "meth": "takeDecision"
},{
  "data": {
    "cost": 3,
    "extras": {},
    "status": "OK"
  },
  "part": "Engine",
  "time": 1571321256426,
  "meth": "takeDecision"
},{
  "data": {
    "action": "echo",
    "parameters": {"direction": "E"}
  },
  "part": "Explorer",
  "time": 1571321256427,
  "meth": "takeDecision"
},{
  "data": {
    "cost": 5,
    "extras": {
      "found": "OUT_OF_RANGE",
      "range": 8
    },
    "status": "OK"
  },
  "part": "Engine",
  "time": 1571321256427,
  "meth": "takeDecision"
},{
  "data": {
    "action": "echo",
    "parameters": {"direction": "W"}
  },
  "part": "Explorer",
  "time": 1571321256427,
  "meth": "takeDecision"
},{
  "data": {
    "cost": 7,
    "extras": {
      "found": "OUT_OF_RANGE",
      "range": 44
    },
    "status": "OK"
  },
  "part": "Engine",
  "time": 1571321256427,
  "meth": "takeDecision"
},{
  "data": {"action": "fly"},
  "part": "Explorer",
  "time": 1571321256427,
  "meth": "takeDecision"
},{
  "data": {
    "cost": 4,
    "extras": {},
    "status": "OK"
  },
  "part": "Engine",
  "time": 1571321256427,
  "meth": "takeDecision"
},{
  "data": {"action": "scan"},
  "part": "Explorer",
  "time": 1571321256427,
  "meth": "takeDecision"
},{
  "data": {
    "cost": 5,
    "extras": {
      "creeks": [],
      "biomes": ["OCEAN"],
      "sites": []
    },
    "status": "OK"
  },
  "part": "Engine",
  "time": 1571321256427,
  "meth": "takeDecision"
},{
  "data": {
    "action": "heading",
    "parameters": {"direction": "W"}
  },
  "part": "Explorer",
  "time": 1571321256428,
  "meth": "takeDecision"
},{
  "data": {
    "cost": 5,
    "extras": {},
    "status": "OK"
  },
  "part": "Engine",
  "time": 1571321256428,
  "meth": "takeDecision"
},{
  "data": {"action": "fly"},
  "part": "Explorer",
  "time": 1571321256428,
  "meth": "takeDecision"
},{
  "data": {
    "cost": 5,
    "extras": {},
    "status": "OK"
  },
  "part": "Engine",
  "time": 1571321256428,
  "meth": "takeDecision"
},{
  "data": {"action": "fly"},
  "part": "Explorer",
  "time": 1571321256428,
  "meth": "takeDecision"
},{
  "data": {
    "cost": 3,
    "extras": {},
    "status": "OK"
  },
  "part": "Engine",
  "time": 1571321256428,
  "meth": "takeDecision"
},{
  "data": {"action": "fly"},
  "part": "Explorer",
  "time": 1571321256428,
  "meth": "takeDecision"
},{
  "data": {
    "cost": 6,
    "extras": {},
    "status": "OK"
  },
  "part": "Engine",
  "time": 1571321256428,
  "meth": "takeDecision"
},{
  "data": {"action": "fly"},
  "part": "Explorer",
  "time": 1571321256428,
  "meth": "takeDecision"
},{
  "data": {
    "cost": 4,
    "extras": {},
    "status": "OK"
  },
  "part": "Engine",
  "time": 1571321256428,
  "meth": "takeDecision"
},{
  "data": {"action": "fly"},
  "part": "Explorer",
  "time": 1571321256428,
  "meth": "takeDecision"
},{
  "data": {
    "cost": 4,
    "extras": {},
    "status": "OK"
  },
  "part": "Engine",
  "time": 1571321256428,
  "meth": "takeDecision"
},{
  "data": {"action": "fly"},
  "part": "Explorer",
  "time": 1571321256428,
  "meth": "takeDecision"
},{
  "data": {
    "cost": 5,
    "extras": {},
    "status": "OK"
  },
  "part": "Engine",
  "time": 1571321256428,
  "meth": "takeDecision"
},{
  "data": {"action": "fly"},
  "part": "Explorer",
  "time": 1571321256428,
  "meth": "takeDecision"
},{
  "data": {
    "cost": 5,
    "extras": {},
    "status": "OK"
  },
  "part": "Engine",
  "time": 1571321256428,
  "meth": "takeDecision"
},{
  "data": {"action": "fly"},
  "part": "Explorer",
  "time": 1571321256428,
  "meth": "takeDecision"
},{
  "data": {
    "cost": 5,
    "extras": {},
    "status": "OK"
  },
  "part": "Engine",
  "time": 1571321256428,
  "meth": "takeDecision"
},{
  "data": {"action": "fly"},
  "part": "Explorer",
  "time": 1571321256428,
  "meth": "takeDecision"
},{
  "data": {
    "cost": 5,
    "extras": {},
    "status": "OK"
  },
  "part": "Engine",
  "time": 1571321256428,
  "meth": "takeDecision"
},{
  "data": {"action": "fly"},
  "part": "Explorer",
  "time": 1571321256428,
  "meth": "takeDecision"
},{
  "data": {
    "cost": 4,
    "extras": {},
    "status": "OK"
  },
  "part": "Engine",
  "time": 1571321256428,
  "meth": "takeDecision"
},{
  "data": {"action": "fly"},
  "part": "Explorer",
  "time": 1571321256428,
  "meth": "takeDecision"
},{
  "data": {
    "cost": 3,
    "extras": {},
    "status": "OK"
  },
  "part": "Engine",
  "time": 1571321256428,
  "meth": "takeDecision"
},{
  "data": {"action": "fly"},
  "part": "Explorer",
  "time": 1571321256428,
  "meth": "takeDecision"
},{
  "data": {
    "cost": 5,
    "extras": {},
    "status": "OK"
  },
  "part": "Engine",
  "time": 1571321256428,
  "meth": "takeDecision"
},{
  "data": {"action": "fly"},
  "part": "Explorer",
  "time": 1571321256428,
  "meth": "takeDecision"
},{
  "data": {
    "cost": 6,
    "extras": {},
    "status": "OK"
  },
  "part": "Engine",
  "time": 1571321256429,
  "meth": "takeDecision"
},{
  "data": {"action": "fly"},
  "part": "Explorer",
  "time": 1571321256429,
  "meth": "takeDecision"
},{
  "data": {
    "cost": 3,
    "extras": {},
    "status": "OK"
  },
  "part": "Engine",
  "time": 1571321256429,
  "meth": "takeDecision"
},{
  "data": {"action": "fly"},
  "part": "Explorer",
  "time": 1571321256429,
  "meth": "takeDecision"
},{
  "data": {
    "cost": 5,
    "extras": {},
    "status": "OK"
  },
  "part": "Engine",
  "time": 1571321256429,
  "meth": "takeDecision"
},{
  "data": {"action": "fly"},
  "part": "Explorer",
  "time": 1571321256429,
  "meth": "takeDecision"
},{
  "data": {
    "cost": 3,
    "extras": {},
    "status": "OK"
  },
  "part": "Engine",
  "time": 1571321256429,
  "meth": "takeDecision"
},{
  "data": {"action": "fly"},
  "part": "Explorer",
  "time": 1571321256429,
  "meth": "takeDecision"
},{
  "data": {
    "cost": 5,
    "extras": {},
    "status": "OK"
  },
  "part": "Engine",
  "time": 1571321256429,
  "meth": "takeDecision"
},{
  "data": {"action": "fly"},
  "part": "Explorer",
  "time": 1571321256429,
  "meth": "takeDecision"
},{
  "data": {
    "cost": 5,
    "extras": {},
    "status": "OK"
  },
  "part": "Engine",
  "time": 1571321256429,
  "meth": "takeDecision"
},{
  "data": {"action": "fly"},
  "part": "Explorer",
  "time": 1571321256429,
  "meth": "takeDecision"
},{
  "data": {
    "cost": 6,
    "extras": {},
    "status": "OK"
  },
  "part": "Engine",
  "time": 1571321256429,
  "meth": "takeDecision"
},{
  "data": {"action": "fly"},
  "part": "Explorer",
  "time": 1571321256429,
  "meth": "takeDecision"
},{
  "data": {
    "cost": 3,
    "extras": {},
    "status": "OK"
  },
  "part": "Engine",
  "time": 1571321256429,
  "meth": "takeDecision"
},{
  "data": {"action": "fly"},
  "part": "Explorer",
  "time": 1571321256429,
  "meth": "takeDecision"
},{
  "data": {
    "cost": 5,
    "extras": {},
    "status": "OK"
  },
  "part": "Engine",
  "time": 1571321256429,
  "meth": "takeDecision"
},{
  "data": {"action": "fly"},
  "part": "Explorer",
  "time": 1571321256430,
  "meth": "takeDecision"
},{
  "data": {
    "cost": 5,
    "extras": {},
    "status": "OK"
  },
  "part": "Engine",
  "time": 1571321256430,
  "meth": "takeDecision"
},{
  "data": {"action": "fly"},
  "part": "Explorer",
  "time": 1571321256430,
  "meth": "takeDecision"
},{
  "data": {
    "cost": 3,
    "extras": {},
    "status": "OK"
  },
  "part": "Engine",
  "time": 1571321256430,
  "meth": "takeDecision"
},{
  "data": {"action": "fly"},
  "part": "Explorer",
  "time": 1571321256430,
  "meth": "takeDecision"
},{
  "data": {
    "cost": 3,
    "extras": {},
    "status": "OK"
  },
  "part": "Engine",
  "time": 1571321256430,
  "meth": "takeDecision"
},{
  "data": {"action": "fly"},
  "part": "Explorer",
  "time": 1571321256430,
  "meth": "takeDecision"
},{
  "data": {
    "cost": 5,
    "extras": {},
    "status": "OK"
  },
  "part": "Engine",
  "time": 1571321256430,
  "meth": "takeDecision"
},{
  "data": {"action": "fly"},
  "part": "Explorer",
  "time": 1571321256430,
  "meth": "takeDecision"
},{
  "data": {
    "cost": 3,
    "extras": {},
    "status": "OK"
  },
  "part": "Engine",
  "time": 1571321256430,
  "meth": "takeDecision"
},{
  "data": {"action": "fly"},
  "part": "Explorer",
  "time": 1571321256430,
  "meth": "takeDecision"
},{
  "data": {
    "cost": 3,
    "extras": {},
    "status": "OK"
  },
  "part": "Engine",
  "time": 1571321256430,
  "meth": "takeDecision"
},{
  "data": {"action": "fly"},
  "part": "Explorer",
  "time": 1571321256430,
  "meth": "takeDecision"
},{
  "data": {
    "cost": 5,
    "extras": {},
    "status": "OK"
  },
  "part": "Engine",
  "time": 1571321256430,
  "meth": "takeDecision"
},{
  "data": {"action": "fly"},
  "part": "Explorer",
  "time": 1571321256430,
  "meth": "takeDecision"
},{
  "data": {
    "cost": 3,
    "extras": {},
    "status": "OK"
  },
  "part": "Engine",
  "time": 1571321256430,
  "meth": "takeDecision"
},{
  "data": {"action": "fly"},
  "part": "Explorer",
  "time": 1571321256430,
  "meth": "takeDecision"
},{
  "data": {
    "cost": 2,
    "extras": {},
    "status": "OK"
  },
  "part": "Engine",
  "time": 1571321256430,
  "meth": "takeDecision"
},{
  "data": {"action": "fly"},
  "part": "Explorer",
  "time": 1571321256430,
  "meth": "takeDecision"
},{
  "data": {
    "cost": 3,
    "extras": {},
    "status": "OK"
  },
  "part": "Engine",
  "time": 1571321256430,
  "meth": "takeDecision"
},{
  "data": {"action": "fly"},
  "part": "Explorer",
  "time": 1571321256430,
  "meth": "takeDecision"
},{
  "data": {
    "cost": 5,
    "extras": {},
    "status": "OK"
  },
  "part": "Engine",
  "time": 1571321256430,
  "meth": "takeDecision"
},{
  "data": {"action": "fly"},
  "part": "Explorer",
  "time": 1571321256430,
  "meth": "takeDecision"
},{
  "data": {
    "cost": 4,
    "extras": {},
    "status": "OK"
  },
  "part": "Engine",
  "time": 1571321256431,
  "meth": "takeDecision"
},{
  "data": {"action": "fly"},
  "part": "Explorer",
  "time": 1571321256431,
  "meth": "takeDecision"
},{
  "data": {
    "cost": 5,
    "extras": {},
    "status": "OK"
  },
  "part": "Engine",
  "time": 1571321256431,
  "meth": "takeDecision"
},{
  "data": {"action": "fly"},
  "part": "Explorer",
  "time": 1571321256431,
  "meth": "takeDecision"
},{
  "data": {
    "cost": 3,
    "extras": {},
    "status": "OK"
  },
  "part": "Engine",
  "time": 1571321256431,
  "meth": "takeDecision"
},{
  "data": {"action": "fly"},
  "part": "Explorer",
  "time": 1571321256431,
  "meth": "takeDecision"
},{
  "data": {
    "cost": 3,
    "extras": {},
    "status": "OK"
  },
  "part": "Engine",
  "time": 1571321256431,
  "meth": "takeDecision"
},{
  "data": {"action": "fly"},
  "part": "Explorer",
  "time": 1571321256431,
  "meth": "takeDecision"
},{
  "data": {
    "cost": 3,
    "extras": {},
    "status": "OK"
  },
  "part": "Engine",
  "time": 1571321256431,
  "meth": "takeDecision"
},{
  "data": {"action": "fly"},
  "part": "Explorer",
  "time": 1571321256431,
  "meth": "takeDecision"
},{
  "data": {
    "cost": 3,
    "extras": {},
    "status": "OK"
  },
  "part": "Engine",
  "time": 1571321256431,
  "meth": "takeDecision"
},{
  "data": {"action": "fly"},
  "part": "Explorer",
  "time": 1571321256431,
  "meth": "takeDecision"
},{
  "data": {
    "cost": 3,
    "extras": {},
    "status": "OK"
  },
  "part": "Engine",
  "time": 1571321256431,
  "meth": "takeDecision"
},{
  "data": {"action": "fly"},
  "part": "Explorer",
  "time": 1571321256431,
  "meth": "takeDecision"
},{
  "data": {
    "cost": 2,
    "extras": {},
    "status": "OK"
  },
  "part": "Engine",
  "time": 1571321256431,
  "meth": "takeDecision"
},{
  "data": {"action": "fly"},
  "part": "Explorer",
  "time": 1571321256431,
  "meth": "takeDecision"
},{
  "data": {
    "cost": 2,
    "extras": {},
    "status": "OK"
  },
  "part": "Engine",
  "time": 1571321256431,
  "meth": "takeDecision"
},{
  "data": {"action": "fly"},
  "part": "Explorer",
  "time": 1571321256431,
  "meth": "takeDecision"
},{
  "data": {
    "cost": 5,
    "extras": {},
    "status": "OK"
  },
  "part": "Engine",
  "time": 1571321256431,
  "meth": "takeDecision"
},{
  "data": {
    "action": "heading",
    "parameters": {"direction": "N"}
  },
  "part": "Explorer",
  "time": 1571321256431,
  "meth": "takeDecision"
},{
  "data": {
    "cost": 4,
    "extras": {},
    "status": "OK"
  },
  "part": "Engine",
  "time": 1571321256431,
  "meth": "takeDecision"
},{
  "data": {"action": "fly"},
  "part": "Explorer",
  "time": 1571321256432,
  "meth": "takeDecision"
},{
  "data": {
    "cost": 5,
    "extras": {},
    "status": "OK"
  },
  "part": "Engine",
  "time": 1571321256432,
  "meth": "takeDecision"
},{
  "data": {"action": "fly"},
  "part": "Explorer",
  "time": 1571321256432,
  "meth": "takeDecision"
},{
  "data": {
    "cost": 4,
    "extras": {},
    "status": "OK"
  },
  "part": "Engine",
  "time": 1571321256432,
  "meth": "takeDecision"
},{
  "data": {"action": "fly"},
  "part": "Explorer",
  "time": 1571321256432,
  "meth": "takeDecision"
},{
  "data": {
    "cost": 4,
    "extras": {},
    "status": "OK"
  },
  "part": "Engine",
  "time": 1571321256432,
  "meth": "takeDecision"
},{
  "data": {"action": "fly"},
  "part": "Explorer",
  "time": 1571321256432,
  "meth": "takeDecision"
},{
  "data": {
    "cost": 5,
    "extras": {},
    "status": "OK"
  },
  "part": "Engine",
  "time": 1571321256432,
  "meth": "takeDecision"
},{
  "data": {"action": "fly"},
  "part": "Explorer",
  "time": 1571321256432,
  "meth": "takeDecision"
},{
  "data": {
    "cost": 5,
    "extras": {},
    "status": "OK"
  },
  "part": "Engine",
  "time": 1571321256432,
  "meth": "takeDecision"
},{
  "data": {"action": "fly"},
  "part": "Explorer",
  "time": 1571321256432,
  "meth": "takeDecision"
},{
  "data": {
    "cost": 4,
    "extras": {},
    "status": "OK"
  },
  "part": "Engine",
  "time": 1571321256432,
  "meth": "takeDecision"
},{
  "data": {"action": "fly"},
  "part": "Explorer",
  "time": 1571321256432,
  "meth": "takeDecision"
},{
  "data": {
    "cost": 6,
    "extras": {},
    "status": "OK"
  },
  "part": "Engine",
  "time": 1571321256432,
  "meth": "takeDecision"
},{
  "data": {"action": "fly"},
  "part": "Explorer",
  "time": 1571321256432,
  "meth": "takeDecision"
},{
  "data": {
    "cost": 4,
    "extras": {},
    "status": "OK"
  },
  "part": "Engine",
  "time": 1571321256432,
  "meth": "takeDecision"
},{
  "data": {"action": "fly"},
  "part": "Explorer",
  "time": 1571321256432,
  "meth": "takeDecision"
},{
  "data": {
    "cost": 4,
    "extras": {},
    "status": "OK"
  },
  "part": "Engine",
  "time": 1571321256432,
  "meth": "takeDecision"
},{
  "data": {"action": "fly"},
  "part": "Explorer",
  "time": 1571321256432,
  "meth": "takeDecision"
},{
  "data": {
    "cost": 5,
    "extras": {},
    "status": "OK"
  },
  "part": "Engine",
  "time": 1571321256432,
  "meth": "takeDecision"
},{
  "data": {"action": "fly"},
  "part": "Explorer",
  "time": 1571321256432,
  "meth": "takeDecision"
},{
  "data": {
    "cost": 4,
    "extras": {},
    "status": "OK"
  },
  "part": "Engine",
  "time": 1571321256432,
  "meth": "takeDecision"
},{
  "data": {"action": "fly"},
  "part": "Explorer",
  "time": 1571321256432,
  "meth": "takeDecision"
},{
  "data": {
    "cost": 5,
    "extras": {},
    "status": "OK"
  },
  "part": "Engine",
  "time": 1571321256432,
  "meth": "takeDecision"
},{
  "data": {"action": "fly"},
  "part": "Explorer",
  "time": 1571321256432,
  "meth": "takeDecision"
},{
  "data": {
    "cost": 4,
    "extras": {},
    "status": "OK"
  },
  "part": "Engine",
  "time": 1571321256432,
  "meth": "takeDecision"
},{
  "data": {"action": "fly"},
  "part": "Explorer",
  "time": 1571321256432,
  "meth": "takeDecision"
},{
  "data": {
    "cost": 5,
    "extras": {},
    "status": "OK"
  },
  "part": "Engine",
  "time": 1571321256432,
  "meth": "takeDecision"
},{
  "data": {"action": "fly"},
  "part": "Explorer",
  "time": 1571321256432,
  "meth": "takeDecision"
},{
  "data": {
    "cost": 4,
    "extras": {},
    "status": "OK"
  },
  "part": "Engine",
  "time": 1571321256432,
  "meth": "takeDecision"
},{
  "data": {"action": "fly"},
  "part": "Explorer",
  "time": 1571321256432,
  "meth": "takeDecision"
},{
  "data": {
    "cost": 4,
    "extras": {},
    "status": "OK"
  },
  "part": "Engine",
  "time": 1571321256432,
  "meth": "takeDecision"
},{
  "data": {"action": "fly"},
  "part": "Explorer",
  "time": 1571321256432,
  "meth": "takeDecision"
},{
  "data": {
    "cost": 5,
    "extras": {},
    "status": "OK"
  },
  "part": "Engine",
  "time": 1571321256433,
  "meth": "takeDecision"
},{
  "data": {"action": "fly"},
  "part": "Explorer",
  "time": 1571321256433,
  "meth": "takeDecision"
},{
  "data": {
    "cost": 5,
    "extras": {},
    "status": "OK"
  },
  "part": "Engine",
  "time": 1571321256433,
  "meth": "takeDecision"
},{
  "data": {"action": "fly"},
  "part": "Explorer",
  "time": 1571321256433,
  "meth": "takeDecision"
},{
  "data": {
    "cost": 6,
    "extras": {},
    "status": "OK"
  },
  "part": "Engine",
  "time": 1571321256433,
  "meth": "takeDecision"
},{
  "data": {"action": "fly"},
  "part": "Explorer",
  "time": 1571321256433,
  "meth": "takeDecision"
},{
  "data": {
    "cost": 3,
    "extras": {},
    "status": "OK"
  },
  "part": "Engine",
  "time": 1571321256433,
  "meth": "takeDecision"
},{
  "data": {"action": "fly"},
  "part": "Explorer",
  "time": 1571321256433,
  "meth": "takeDecision"
},{
  "data": {
    "cost": 6,
    "extras": {},
    "status": "OK"
  },
  "part": "Engine",
  "time": 1571321256433,
  "meth": "takeDecision"
},{
  "data": {"action": "fly"},
  "part": "Explorer",
  "time": 1571321256433,
  "meth": "takeDecision"
},{
  "data": {
    "cost": 5,
    "extras": {},
    "status": "OK"
  },
  "part": "Engine",
  "time": 1571321256433,
  "meth": "takeDecision"
},{
  "data": {"action": "fly"},
  "part": "Explorer",
  "time": 1571321256433,
  "meth": "takeDecision"
},{
  "data": {
    "cost": 5,
    "extras": {},
    "status": "OK"
  },
  "part": "Engine",
  "time": 1571321256433,
  "meth": "takeDecision"
},{
  "data": {"action": "fly"},
  "part": "Explorer",
  "time": 1571321256433,
  "meth": "takeDecision"
},{
  "data": {
    "cost": 2,
    "extras": {},
    "status": "OK"
  },
  "part": "Engine",
  "time": 1571321256433,
  "meth": "takeDecision"
},{
  "data": {"action": "fly"},
  "part": "Explorer",
  "time": 1571321256433,
  "meth": "takeDecision"
},{
  "data": {
    "cost": 3,
    "extras": {},
    "status": "OK"
  },
  "part": "Engine",
  "time": 1571321256433,
  "meth": "takeDecision"
},{
  "data": {"action": "fly"},
  "part": "Explorer",
  "time": 1571321256433,
  "meth": "takeDecision"
},{
  "data": {
    "cost": 3,
    "extras": {},
    "status": "OK"
  },
  "part": "Engine",
  "time": 1571321256433,
  "meth": "takeDecision"
},{
  "data": {"action": "fly"},
  "part": "Explorer",
  "time": 1571321256433,
  "meth": "takeDecision"
},{
  "data": {
    "cost": 2,
    "extras": {},
    "status": "OK"
  },
  "part": "Engine",
  "time": 1571321256433,
  "meth": "takeDecision"
},{
  "data": {"action": "fly"},
  "part": "Explorer",
  "time": 1571321256433,
  "meth": "takeDecision"
},{
  "data": {
    "cost": 5,
    "extras": {},
    "status": "OK"
  },
  "part": "Engine",
  "time": 1571321256433,
  "meth": "takeDecision"
},{
  "data": {"action": "fly"},
  "part": "Explorer",
  "time": 1571321256433,
  "meth": "takeDecision"
},{
  "data": {
    "cost": 6,
    "extras": {},
    "status": "OK"
  },
  "part": "Engine",
  "time": 1571321256433,
  "meth": "takeDecision"
},{
  "data": {"action": "fly"},
  "part": "Explorer",
  "time": 1571321256433,
  "meth": "takeDecision"
},{
  "data": {
    "cost": 4,
    "extras": {},
    "status": "OK"
  },
  "part": "Engine",
  "time": 1571321256433,
  "meth": "takeDecision"
},{
  "data": {"action": "fly"},
  "part": "Explorer",
  "time": 1571321256433,
  "meth": "takeDecision"
},{
  "data": {
    "cost": 4,
    "extras": {},
    "status": "OK"
  },
  "part": "Engine",
  "time": 1571321256433,
  "meth": "takeDecision"
},{
  "data": {"action": "fly"},
  "part": "Explorer",
  "time": 1571321256433,
  "meth": "takeDecision"
},{
  "data": {
    "cost": 6,
    "extras": {},
    "status": "OK"
  },
  "part": "Engine",
  "time": 1571321256433,
  "meth": "takeDecision"
},{
  "data": {"action": "fly"},
  "part": "Explorer",
  "time": 1571321256433,
  "meth": "takeDecision"
},{
  "data": {
    "cost": 2,
    "extras": {},
    "status": "OK"
  },
  "part": "Engine",
  "time": 1571321256433,
  "meth": "takeDecision"
},{
  "data": {"action": "fly"},
  "part": "Explorer",
  "time": 1571321256433,
  "meth": "takeDecision"
},{
  "data": {
    "cost": 2,
    "extras": {},
    "status": "OK"
  },
  "part": "Engine",
  "time": 1571321256433,
  "meth": "takeDecision"
},{
  "data": {"action": "fly"},
  "part": "Explorer",
  "time": 1571321256433,
  "meth": "takeDecision"
},{
  "data": {
    "cost": 6,
    "extras": {},
    "status": "OK"
  },
  "part": "Engine",
  "time": 1571321256433,
  "meth": "takeDecision"
},{
  "data": {"action": "fly"},
  "part": "Explorer",
  "time": 1571321256433,
  "meth": "takeDecision"
},{
  "data": {
    "cost": 4,
    "extras": {},
    "status": "OK"
  },
  "part": "Engine",
  "time": 1571321256434,
  "meth": "takeDecision"
},{
  "data": {"action": "fly"},
  "part": "Explorer",
  "time": 1571321256434,
  "meth": "takeDecision"
},{
  "data": {
    "cost": 4,
    "extras": {},
    "status": "OK"
  },
  "part": "Engine",
  "time": 1571321256434,
  "meth": "takeDecision"
},{
  "data": {"action": "fly"},
  "part": "Explorer",
  "time": 1571321256434,
  "meth": "takeDecision"
},{
  "data": {
    "cost": 4,
    "extras": {},
    "status": "OK"
  },
  "part": "Engine",
  "time": 1571321256434,
  "meth": "takeDecision"
},{
  "data": {"action": "fly"},
  "part": "Explorer",
  "time": 1571321256434,
  "meth": "takeDecision"
},{
  "data": {
    "cost": 5,
    "extras": {},
    "status": "OK"
  },
  "part": "Engine",
  "time": 1571321256434,
  "meth": "takeDecision"
},{
  "data": {"action": "fly"},
  "part": "Explorer",
  "time": 1571321256434,
  "meth": "takeDecision"
},{
  "data": {
    "cost": 4,
    "extras": {},
    "status": "OK"
  },
  "part": "Engine",
  "time": 1571321256434,
  "meth": "takeDecision"
},{
  "data": {"action": "fly"},
  "part": "Explorer",
  "time": 1571321256434,
  "meth": "takeDecision"
},{
  "data": {
    "cost": 4,
    "extras": {},
    "status": "OK"
  },
  "part": "Engine",
  "time": 1571321256434,
  "meth": "takeDecision"
},{
  "data": {"action": "fly"},
  "part": "Explorer",
  "time": 1571321256434,
  "meth": "takeDecision"
},{
  "data": {
    "cost": 5,
    "extras": {},
    "status": "OK"
  },
  "part": "Engine",
  "time": 1571321256434,
  "meth": "takeDecision"
},{
  "data": {"action": "fly"},
  "part": "Explorer",
  "time": 1571321256434,
  "meth": "takeDecision"
},{
  "data": {
    "cost": 3,
    "extras": {},
    "status": "OK"
  },
  "part": "Engine",
  "time": 1571321256434,
  "meth": "takeDecision"
},{
  "data": {"action": "fly"},
  "part": "Explorer",
  "time": 1571321256434,
  "meth": "takeDecision"
},{
  "data": {
    "cost": 5,
    "extras": {},
    "status": "OK"
  },
  "part": "Engine",
  "time": 1571321256434,
  "meth": "takeDecision"
},{
  "data": {"action": "stop"},
  "part": "Explorer",
  "time": 1571321256434,
  "meth": "takeDecision"
},{
  "data": {
    "cost": 4,
    "extras": {},
    "status": "OK"
  },
  "part": "Engine",
  "time": 1571321256434,
  "meth": "takeDecision"
}]