[
    {
        "uid": "cc9fb16f-8f6d-4787-b7b4-2201c3a1e6e0",
        "kind": "Creek",
        "x": 468.2596798826745,
        "y": 329.2598469825142
    },
    {
        "uid": "a3cc410c-be85-436f-b250-0ad46f291eed",
        "kind": "Creek",
        "x": 400.4614956987327,
        "y": 390.3214413995525
    },
    {
        "uid": "97bf351b-2ee6-4745-b87d-fb9590e411c4",
        "kind": "Creek",
        "x": 415.91367684815975,
        "y": 683.8967778481763
    },
    {
        "uid": "2a6efa65-3c60-4fe5-a868-8c89752f0f90",
        "kind": "Creek",
        "x": 559.6040366462531,
        "y": 882.5456798679087
    },
    {
        "uid": "ce4a8384-7287-40a6-bade-290e8ec21fb1",
        "kind": "EmergencySite",
        "x": 1130.0253058860442,
        "y": 1226.230874483747
    },
    {
        "uid": "ca7fda85-188b-47e6-ad56-91112fea7250",
        "kind": "Creek",
        "x": 488.9393820391075,
        "y": 792.4068745444174
    },
    {
        "uid": "097bfde1-b1ac-4670-b3c4-a1926300fd04",
        "kind": "Creek",
        "x": 824.0082721855549,
        "y": 495.64252810291407
    },
    {
        "uid": "02fc6e28-8c7e-4318-9fd3-71ace4d4d61a",
        "kind": "Creek",
        "x": 378.427574846117,
        "y": 643.864801703796
    },
    {
        "uid": "5be76979-4c87-400c-97b5-a8466b33a454",
        "kind": "Creek",
        "x": 1243.3959963978673,
        "y": 1167.553133744158
    },
    {
        "uid": "f11816c9-f441-4086-8aa0-2bbf4f1abe34",
        "kind": "Creek",
        "x": 1208.542142516696,
        "y": 1236.422765099077
    },
    {
        "uid": "89e1fbf0-27d1-45b1-b7a2-911d2785814a",
        "kind": "Creek",
        "x": 660.3827965271728,
        "y": 384.91444660701023
    }
]